{"player_id":"c0nu","sack_id":"211570","name":"Cesar Cruz","updated":"2026-03-24","total":4,"matches":[{"date":"20240914","tournament":"Davis Cup WG2 R1: BUL vs ESA","surface":"Clay","level":"D","round":"RR","result":"L","opponent":"Yanaki Milev","opponent_id":"210200","score":"6-3 4-6 6-3","best_of":"3","minutes":"148","rank":"","opp_rank":"445"},{"date":"20230916","tournament":"Davis Cup WG2 R1: ESA vs IRL","surface":"Clay","level":"D","round":"RR","result":"L","opponent":"Conor Gannon","opponent_id":"149843","score":"6-1 6-0","best_of":"3","minutes":"","rank":"","opp_rank":""},{"date":"20220917","tournament":"Davis Cup WG2 R1: DEN vs ESA","surface":"Hard","level":"D","round":"RR","result":"L","opponent":"Johannes Ingildsen","opponent_id":"134087","score":"6-4 6-4","best_of":"3","minutes":"","rank":"","opp_rank":"638"},{"date":"20220917","tournament":"Davis Cup WG2 R1: DEN vs ESA","surface":"Hard","level":"D","round":"RR","result":"L","opponent":"Elmer Moller","opponent_id":"209284","score":"6-1 6-0","best_of":"3","minutes":"","rank":"","opp_rank":"874"}]}