{
  "player_id": "b0u4",
  "gs_id": "208825",
  "player_name": "Nicolai Budkov Kjaer",
  "source": "goalserve-full",
  "updated": "2026-03-26T15:21:44.692Z",
  "matches": [
    {
      "date": "20260311",
      "tournament": "Cherbourg",
      "surface": "Hard",
      "level": "C",
      "round": "R32",
      "best_of": "3",
      "rank": "",
      "opp_rank": "",
      "result": "L",
      "opponent": "R. Bertola",
      "score": "7-5 6-1"
    },
    {
      "date": "20260105",
      "tournament": "Canberra",
      "surface": "Hard",
      "level": "C",
      "round": "R32",
      "best_of": "3",
      "rank": "",
      "opp_rank": "",
      "result": "L",
      "opponent": "A. Blockx",
      "score": "6-2 6-3"
    },
    {
      "date": "20251220",
      "tournament": "Next Gen Finals - Jeddah",
      "surface": "Hard",
      "level": "B",
      "round": "SF",
      "best_of": "3",
      "rank": "",
      "opp_rank": "",
      "result": "L",
      "opponent": "A. Blockx",
      "score": "3(4)-4(7) 3(8)-4(10) 2-4"
    },
    {
      "date": "20251005",
      "tournament": "Mouilleron-Le-Captif",
      "surface": "Hard",
      "level": "C",
      "round": "F",
      "best_of": "3",
      "rank": "",
      "opp_rank": "",
      "result": "W",
      "opponent": "P. Kypson",
      "score": "0-6 3-6"
    },
    {
      "date": "20251004",
      "tournament": "Mouilleron-Le-Captif",
      "surface": "Hard",
      "level": "C",
      "round": "SF",
      "best_of": "3",
      "rank": "",
      "opp_rank": "",
      "result": "W",
      "opponent": "C. Chidekh",
      "score": "6-1 4-6 6-2"
    },
    {
      "date": "20251003",
      "tournament": "Mouilleron-Le-Captif",
      "surface": "Hard",
      "level": "C",
      "round": "QF",
      "best_of": "3",
      "rank": "",
      "opp_rank": "",
      "result": "W",
      "opponent": "F. Passaro",
      "score": "6-4 6-4"
    },
    {
      "date": "20251002",
      "tournament": "Mouilleron-Le-Captif",
      "surface": "Hard",
      "level": "C",
      "round": "R16",
      "best_of": "3",
      "rank": "",
      "opp_rank": "",
      "result": "W",
      "opponent": "L. Massard",
      "score": "6-3 6-2"
    },
    {
      "date": "20250930",
      "tournament": "Mouilleron-Le-Captif",
      "surface": "Hard",
      "level": "C",
      "round": "R32",
      "best_of": "3",
      "rank": "",
      "opp_rank": "",
      "result": "W",
      "opponent": "N. Vylegzhanin",
      "score": "6-1 6-3"
    },
    {
      "date": "20250814",
      "tournament": "Todi",
      "surface": "Hard",
      "level": "C",
      "round": "QF",
      "best_of": "3",
      "rank": "",
      "opp_rank": "",
      "result": "L",
      "opponent": "V. Vacherot",
      "score": "6-1 6-3"
    },
    {
      "date": "20250813",
      "tournament": "Todi",
      "surface": "Hard",
      "level": "C",
      "round": "R16",
      "best_of": "3",
      "rank": "",
      "opp_rank": "",
      "result": "W",
      "opponent": "M. Pucinelli de Almeida",
      "score": "7(7)-6(2) 3-0 ret."
    },
    {
      "date": "20250811",
      "tournament": "Todi",
      "surface": "Hard",
      "level": "C",
      "round": "R32",
      "best_of": "3",
      "rank": "",
      "opp_rank": "",
      "result": "W",
      "opponent": "J. B. Torres",
      "score": "6-2 4-6 7(7)-6(5)"
    },
    {
      "date": "20250616",
      "tournament": "Nottingham",
      "surface": "Hard",
      "level": "C",
      "round": "R32",
      "best_of": "3",
      "rank": "",
      "opp_rank": "",
      "result": "L",
      "opponent": "M. Landaluce",
      "score": "2-6 6-2 2-6"
    },
    {
      "date": "20250526",
      "tournament": "Vicenza",
      "surface": "Hard",
      "level": "C",
      "round": "F",
      "best_of": "3",
      "rank": "",
      "opp_rank": "",
      "result": "L",
      "opponent": "F. Bondioli",
      "score": "3-6 5-7"
    },
    {
      "date": "20250525",
      "tournament": "Vicenza",
      "surface": "Hard",
      "level": "C",
      "round": "SF",
      "best_of": "3",
      "rank": "",
      "opp_rank": "",
      "result": "W",
      "opponent": "M. Giunta",
      "score": "6-2 4-6 2-6"
    },
    {
      "date": "20250509",
      "tournament": "Prague",
      "surface": "Hard",
      "level": "C",
      "round": "QF",
      "best_of": "3",
      "rank": "",
      "opp_rank": "",
      "result": "L",
      "opponent": "M. Landaluce",
      "score": "6-4 6-3"
    },
    {
      "date": "20250507",
      "tournament": "Prague",
      "surface": "Hard",
      "level": "C",
      "round": "R16",
      "best_of": "3",
      "rank": "",
      "opp_rank": "",
      "result": "W",
      "opponent": "C. Hemery",
      "score": "6-2 6-3"
    },
    {
      "date": "20250505",
      "tournament": "Prague",
      "surface": "Hard",
      "level": "C",
      "round": "R32",
      "best_of": "3",
      "rank": "",
      "opp_rank": "",
      "result": "W",
      "opponent": "A. Moro Canas",
      "score": "5-7 1-6"
    },
    {
      "date": "20250223",
      "tournament": "Glasgow",
      "surface": "Hard",
      "level": "C",
      "round": "F",
      "best_of": "3",
      "rank": "",
      "opp_rank": "",
      "result": "W",
      "opponent": "V. Durasovic",
      "score": "6-4 6-3"
    },
    {
      "date": "20250222",
      "tournament": "Glasgow",
      "surface": "Hard",
      "level": "C",
      "round": "SF",
      "best_of": "3",
      "rank": "",
      "opp_rank": "",
      "result": "W",
      "opponent": "M. H. Rehberg",
      "score": "3-6 6(3)-7(7)"
    },
    {
      "date": "20250221",
      "tournament": "Glasgow",
      "surface": "Hard",
      "level": "C",
      "round": "QF",
      "best_of": "3",
      "rank": "",
      "opp_rank": "",
      "result": "W",
      "opponent": "L. Draxl",
      "score": "3-6 6-1 1-6"
    },
    {
      "date": "20250220",
      "tournament": "Glasgow",
      "surface": "Hard",
      "level": "C",
      "round": "R16",
      "best_of": "3",
      "rank": "",
      "opp_rank": "",
      "result": "W",
      "opponent": "R. Brancaccio",
      "score": "4-6 6(7)-7(9)"
    },
    {
      "date": "20250218",
      "tournament": "Glasgow",
      "surface": "Hard",
      "level": "C",
      "round": "R32",
      "best_of": "3",
      "rank": "",
      "opp_rank": "",
      "result": "W",
      "opponent": "H. Grenier",
      "score": "6-3 3-6 6-2"
    }
  ]
}