{
  "player_id": "f0ck",
  "gs_id": "39023",
  "player_name": "Andrew Fenty",
  "source": "goalserve-full",
  "updated": "2026-03-26T23:49:18.899Z",
  "matches": [
    {
      "date": "20250425",
      "tournament": "M15 Vero Beach",
      "surface": "Hard",
      "level": "I",
      "round": "QF",
      "best_of": "3",
      "rank": "",
      "opp_rank": "",
      "result": "L",
      "opponent": "W. Grant",
      "score": "4-6 5-7"
    },
    {
      "date": "20250424",
      "tournament": "M15 Vero Beach",
      "surface": "Hard",
      "level": "I",
      "round": "R16",
      "best_of": "3",
      "rank": "",
      "opp_rank": "",
      "result": "W",
      "opponent": "J. Flores",
      "score": "2-6 2-6"
    },
    {
      "date": "20250423",
      "tournament": "M15 Vero Beach",
      "surface": "Hard",
      "level": "I",
      "round": "R32",
      "best_of": "3",
      "rank": "",
      "opp_rank": "",
      "result": "W",
      "opponent": "S. Kirchheimer",
      "score": "6-2 6-1"
    }
  ]
}