{
  "player_id": "g0im",
  "gs_id": "154577",
  "player_name": "Gian Gruenig",
  "source": "goalserve-full",
  "updated": "2026-03-27T04:58:27.992Z",
  "matches": [
    {
      "date": "20251008",
      "tournament": "M25 Santa Margherita di Pula 10",
      "surface": "Hard",
      "level": "I",
      "round": "R16",
      "best_of": "3",
      "rank": "",
      "opp_rank": "",
      "result": "L",
      "opponent": "A. Chepelev",
      "score": "2-6 1-6"
    },
    {
      "date": "20251007",
      "tournament": "M25 Santa Margherita di Pula 10",
      "surface": "Hard",
      "level": "I",
      "round": "R32",
      "best_of": "3",
      "rank": "",
      "opp_rank": "",
      "result": "W",
      "opponent": "G. Gandolfi",
      "score": "6-2 2-6 6(5)-7(7)"
    }
  ]
}