{
  "player_id": "ge28",
  "gs_id": "6938",
  "player_name": "Ivan Gakhov",
  "source": "goalserve-full",
  "updated": "2026-03-27T01:50:11.964Z",
  "matches": [
    {
      "date": "20260317",
      "tournament": "Murcia",
      "surface": "Hard",
      "level": "C",
      "round": "R32",
      "best_of": "3",
      "rank": "",
      "opp_rank": "",
      "result": "L",
      "opponent": "Ch. Negritu",
      "score": "6-1 6-2"
    },
    {
      "date": "20260225",
      "tournament": "Lugano",
      "surface": "Hard",
      "level": "C",
      "round": "R16",
      "best_of": "3",
      "rank": "",
      "opp_rank": "",
      "result": "L",
      "opponent": "Z. Piros",
      "score": "7(7)-6(1) 6-3"
    },
    {
      "date": "20260224",
      "tournament": "Lugano",
      "surface": "Hard",
      "level": "C",
      "round": "R32",
      "best_of": "3",
      "rank": "",
      "opp_rank": "",
      "result": "W",
      "opponent": "G. Piraino",
      "score": "2-6 6-2 7(8)-6(6)"
    },
    {
      "date": "20260130",
      "tournament": "Oeiras 2",
      "surface": "Hard",
      "level": "C",
      "round": "QF",
      "best_of": "3",
      "rank": "",
      "opp_rank": "",
      "result": "L",
      "opponent": "F. Ferreira Silva",
      "score": "6-3 6-4"
    },
    {
      "date": "20260128",
      "tournament": "Oeiras 2",
      "surface": "Hard",
      "level": "C",
      "round": "R16",
      "best_of": "3",
      "rank": "",
      "opp_rank": "",
      "result": "W",
      "opponent": "M. Rosenkranz",
      "score": "6-4 7(7)-6(2)"
    },
    {
      "date": "20260126",
      "tournament": "Oeiras 2",
      "surface": "Hard",
      "level": "C",
      "round": "R32",
      "best_of": "3",
      "rank": "",
      "opp_rank": "",
      "result": "W",
      "opponent": "J. Rodionov",
      "score": "5-7 3-6"
    },
    {
      "date": "20251125",
      "tournament": "Maia",
      "surface": "Hard",
      "level": "C",
      "round": "R32",
      "best_of": "3",
      "rank": "",
      "opp_rank": "",
      "result": "L",
      "opponent": "A. Martin",
      "score": "3-6 6-4 6-4"
    },
    {
      "date": "20251106",
      "tournament": "Lima 2",
      "surface": "Hard",
      "level": "C",
      "round": "R16",
      "best_of": "3",
      "rank": "",
      "opp_rank": "",
      "result": "L",
      "opponent": "C. Garin",
      "score": "6-3 6-3"
    },
    {
      "date": "20251104",
      "tournament": "Lima 2",
      "surface": "Hard",
      "level": "C",
      "round": "R32",
      "best_of": "3",
      "rank": "",
      "opp_rank": "",
      "result": "W",
      "opponent": "A. Huertas Del Pino Cordova",
      "score": "6-3 4-6 6-3"
    },
    {
      "date": "20250919",
      "tournament": "M15 Melilla",
      "surface": "Hard",
      "level": "I",
      "round": "QF",
      "best_of": "3",
      "rank": "",
      "opp_rank": "",
      "result": "L",
      "opponent": "V. C. Loureiro J.",
      "score": "7(8)-6(6) 3-6 6-2"
    },
    {
      "date": "20250918",
      "tournament": "M15 Melilla",
      "surface": "Hard",
      "level": "I",
      "round": "R16",
      "best_of": "3",
      "rank": "",
      "opp_rank": "",
      "result": "W",
      "opponent": "E. Villoslada",
      "score": "6-2 6-4"
    },
    {
      "date": "20250917",
      "tournament": "M15 Melilla",
      "surface": "Hard",
      "level": "I",
      "round": "R32",
      "best_of": "3",
      "rank": "",
      "opp_rank": "",
      "result": "W",
      "opponent": "P. Petrov",
      "score": "6-0 6-3"
    },
    {
      "date": "20250901",
      "tournament": "Tulln",
      "surface": "Hard",
      "level": "C",
      "round": "R32",
      "best_of": "3",
      "rank": "",
      "opp_rank": "",
      "result": "L",
      "opponent": "M. Trungelliti",
      "score": "4-6 2-6"
    },
    {
      "date": "20250730",
      "tournament": "Astana",
      "surface": "Hard",
      "level": "C",
      "round": "R16",
      "best_of": "3",
      "rank": "",
      "opp_rank": "",
      "result": "L",
      "opponent": "K. Singh",
      "score": "6-3 7(9)-6(7)"
    },
    {
      "date": "20250729",
      "tournament": "Astana",
      "surface": "Hard",
      "level": "C",
      "round": "R32",
      "best_of": "3",
      "rank": "",
      "opp_rank": "",
      "result": "W",
      "opponent": "E. Arutiunian",
      "score": "6-1 6(4)-7(7) 7-5"
    },
    {
      "date": "20250713",
      "tournament": "M25 The Hague",
      "surface": "Hard",
      "level": "I",
      "round": "F",
      "best_of": "3",
      "rank": "",
      "opp_rank": "",
      "result": "W",
      "opponent": "R. Nijboer",
      "score": "3-6 6-4 7-5"
    },
    {
      "date": "20250712",
      "tournament": "M25 The Hague",
      "surface": "Hard",
      "level": "I",
      "round": "SF",
      "best_of": "3",
      "rank": "",
      "opp_rank": "",
      "result": "W",
      "opponent": "J. D. Hara Friend",
      "score": "4-6 7(7)-6(2) 7(7)-6(0)"
    },
    {
      "date": "20250711",
      "tournament": "M25 The Hague",
      "surface": "Hard",
      "level": "I",
      "round": "QF",
      "best_of": "3",
      "rank": "",
      "opp_rank": "",
      "result": "W",
      "opponent": "E. Vanshelboim",
      "score": "6-2 6-1"
    },
    {
      "date": "20250710",
      "tournament": "M25 The Hague",
      "surface": "Hard",
      "level": "I",
      "round": "R16",
      "best_of": "3",
      "rank": "",
      "opp_rank": "",
      "result": "W",
      "opponent": "A. Forger",
      "score": "7-5 6-4"
    },
    {
      "date": "20250709",
      "tournament": "M25 The Hague",
      "surface": "Hard",
      "level": "I",
      "round": "R32",
      "best_of": "3",
      "rank": "",
      "opp_rank": "",
      "result": "W",
      "opponent": "D. Donders",
      "score": "6-2 7-5"
    },
    {
      "date": "20250425",
      "tournament": "M25 Angers",
      "surface": "Hard",
      "level": "I",
      "round": "QF",
      "best_of": "3",
      "rank": "",
      "opp_rank": "",
      "result": "L",
      "opponent": "S. Perez Contri",
      "score": "2-6 6-3 6-4"
    },
    {
      "date": "20250424",
      "tournament": "M25 Angers",
      "surface": "Hard",
      "level": "I",
      "round": "R16",
      "best_of": "3",
      "rank": "",
      "opp_rank": "",
      "result": "W",
      "opponent": "T. Deschamps",
      "score": "6-3 7-5"
    },
    {
      "date": "20250423",
      "tournament": "M25 Angers",
      "surface": "Hard",
      "level": "I",
      "round": "R32",
      "best_of": "3",
      "rank": "",
      "opp_rank": "",
      "result": "W",
      "opponent": "D. Salazar",
      "score": "6-3 7-5"
    },
    {
      "date": "20250405",
      "tournament": "M25 Reus",
      "surface": "Hard",
      "level": "I",
      "round": "SF",
      "best_of": "3",
      "rank": "",
      "opp_rank": "",
      "result": "L",
      "opponent": "N. Sanchez Izquierdo",
      "score": "1-6 6-3 7-5"
    },
    {
      "date": "20250404",
      "tournament": "M25 Reus",
      "surface": "Hard",
      "level": "I",
      "round": "QF",
      "best_of": "3",
      "rank": "",
      "opp_rank": "",
      "result": "W",
      "opponent": "A. Sanchez Quilez",
      "score": "2-6 6-4 6-4"
    },
    {
      "date": "20250403",
      "tournament": "M25 Reus",
      "surface": "Hard",
      "level": "I",
      "round": "R16",
      "best_of": "3",
      "rank": "",
      "opp_rank": "",
      "result": "W",
      "opponent": "D. Fernandez Flores",
      "score": "6-3 6-4"
    },
    {
      "date": "20250402",
      "tournament": "M25 Reus",
      "surface": "Hard",
      "level": "I",
      "round": "R32",
      "best_of": "3",
      "rank": "",
      "opp_rank": "",
      "result": "W",
      "opponent": "A. Jimenez",
      "score": "6-3 6-4"
    },
    {
      "date": "20250322",
      "tournament": "Murcia",
      "surface": "Hard",
      "level": "C",
      "round": "SF",
      "best_of": "3",
      "rank": "",
      "opp_rank": "",
      "result": "L",
      "opponent": "J. De Jong",
      "score": "7-5 6-1"
    },
    {
      "date": "20250321",
      "tournament": "Murcia",
      "surface": "Hard",
      "level": "C",
      "round": "QF",
      "best_of": "3",
      "rank": "",
      "opp_rank": "",
      "result": "W",
      "opponent": "D. Yevseyev",
      "score": "6-1 3-6 4-6"
    },
    {
      "date": "20250320",
      "tournament": "Murcia",
      "surface": "Hard",
      "level": "C",
      "round": "R16",
      "best_of": "3",
      "rank": "",
      "opp_rank": "",
      "result": "W",
      "opponent": "N. Budkov Kjaer",
      "score": "4-6 6(2)-7(7)"
    },
    {
      "date": "20250319",
      "tournament": "Murcia",
      "surface": "Hard",
      "level": "C",
      "round": "R32",
      "best_of": "3",
      "rank": "",
      "opp_rank": "",
      "result": "W",
      "opponent": "P. Carreno-Busta",
      "score": "6-3 6-4"
    },
    {
      "date": "20250202",
      "tournament": "Lille",
      "surface": "Hard",
      "level": "C",
      "round": "SF",
      "best_of": "3",
      "rank": "",
      "opp_rank": "",
      "result": "L",
      "opponent": "A. Bouquier",
      "score": "3-6 5-6 ret."
    },
    {
      "date": "20250108",
      "tournament": "Oeiras",
      "surface": "Hard",
      "level": "C",
      "round": "R16",
      "best_of": "3",
      "rank": "",
      "opp_rank": "",
      "result": "L",
      "opponent": "M. H. Rehberg",
      "score": "7-5 6-3"
    },
    {
      "date": "20250107",
      "tournament": "Oeiras",
      "surface": "Hard",
      "level": "C",
      "round": "R32",
      "best_of": "3",
      "rank": "",
      "opp_rank": "",
      "result": "W",
      "opponent": "P. Araujo",
      "score": "4-6 6-3 2-6"
    },
    {
      "date": "20250106",
      "tournament": "Oeiras",
      "surface": "Hard",
      "level": "C",
      "round": "F",
      "best_of": "3",
      "rank": "",
      "opp_rank": "",
      "result": "W",
      "opponent": "C. Harper",
      "score": "6-1 4-6 6-4"
    },
    {
      "date": "20250105",
      "tournament": "Oeiras",
      "surface": "Hard",
      "level": "C",
      "round": "SF",
      "best_of": "3",
      "rank": "",
      "opp_rank": "",
      "result": "W",
      "opponent": "D. Marques",
      "score": "6-1 6-1"
    },
    {
      "date": "20241126",
      "tournament": "Maia",
      "surface": "Hard",
      "level": "C",
      "round": "R32",
      "best_of": "3",
      "rank": "",
      "opp_rank": "",
      "result": "L",
      "opponent": "N. Alvarez Varona",
      "score": "3-6 5-7"
    },
    {
      "date": "20240906",
      "tournament": "Tulln Challenger Men",
      "surface": "Hard",
      "level": "C",
      "round": "QF",
      "best_of": "3",
      "rank": "",
      "opp_rank": "",
      "result": "L",
      "opponent": "J. Nicod",
      "score": "6-3 5-7 6-2"
    },
    {
      "date": "20240905",
      "tournament": "Tulln Challenger Men",
      "surface": "Hard",
      "level": "C",
      "round": "R16",
      "best_of": "3",
      "rank": "",
      "opp_rank": "",
      "result": "W",
      "opponent": "M. Topo",
      "score": "6(7)-7(9) 2-6"
    },
    {
      "date": "20240904",
      "tournament": "Tulln Challenger Men",
      "surface": "Hard",
      "level": "C",
      "round": "R32",
      "best_of": "3",
      "rank": "",
      "opp_rank": "",
      "result": "W",
      "opponent": "J. J. Schwaerzler",
      "score": "6(2)-7(7) 6-4 6-3"
    },
    {
      "date": "20240902",
      "tournament": "Tulln Challenger Men",
      "surface": "Hard",
      "level": "C",
      "round": "F",
      "best_of": "3",
      "rank": "",
      "opp_rank": "",
      "result": "W",
      "opponent": "R. Strombachs",
      "score": "6(7)-7(9) 6-4 6-3"
    },
    {
      "date": "20240901",
      "tournament": "Tulln Challenger Men",
      "surface": "Hard",
      "level": "C",
      "round": "SF",
      "best_of": "3",
      "rank": "",
      "opp_rank": "",
      "result": "W",
      "opponent": "M. Neuchrist",
      "score": "6-4 6-4"
    },
    {
      "date": "20240611",
      "tournament": "Bratislava Challenger Men",
      "surface": "Hard",
      "level": "C",
      "round": "R32",
      "best_of": "3",
      "rank": "",
      "opp_rank": "",
      "result": "L",
      "opponent": "M. Trungelliti",
      "score": "6-4 6-1"
    },
    {
      "date": "20240513",
      "tournament": "Turin 2 Challenger Men",
      "surface": "Hard",
      "level": "C",
      "round": "SF",
      "best_of": "3",
      "rank": "",
      "opp_rank": "",
      "result": "L",
      "opponent": "M. Bellucci",
      "score": "7(7)-6(0) 6-2"
    },
    {
      "date": "20240408",
      "tournament": "Split",
      "surface": "Hard",
      "level": "C",
      "round": "R32",
      "best_of": "3",
      "rank": "",
      "opp_rank": "",
      "result": "L",
      "opponent": "Q. Halys",
      "score": "6-3 6-4"
    },
    {
      "date": "20240404",
      "tournament": "Barcelona",
      "surface": "Hard",
      "level": "C",
      "round": "R16",
      "best_of": "3",
      "rank": "",
      "opp_rank": "",
      "result": "L",
      "opponent": "J. Barranco Cosano",
      "score": "1-6 6-3 4-6"
    },
    {
      "date": "20240402",
      "tournament": "Barcelona",
      "surface": "Hard",
      "level": "C",
      "round": "R32",
      "best_of": "3",
      "rank": "",
      "opp_rank": "",
      "result": "W",
      "opponent": "A. Moro Canas",
      "score": "5-7 2-6"
    },
    {
      "date": "20240320",
      "tournament": "Murcia Challenger Men",
      "surface": "Hard",
      "level": "C",
      "round": "R16",
      "best_of": "3",
      "rank": "",
      "opp_rank": "",
      "result": "L",
      "opponent": "P. Llamas Ruiz",
      "score": "3-6 5-7"
    },
    {
      "date": "20240319",
      "tournament": "Murcia Challenger Men",
      "surface": "Hard",
      "level": "C",
      "round": "R32",
      "best_of": "3",
      "rank": "",
      "opp_rank": "",
      "result": "W",
      "opponent": "C. H. Tseng",
      "score": "4-6 6-3 3-6"
    },
    {
      "date": "20240220",
      "tournament": "Pau Challenger Men",
      "surface": "Hard",
      "level": "C",
      "round": "R32",
      "best_of": "3",
      "rank": "",
      "opp_rank": "",
      "result": "L",
      "opponent": "J. K. Trotter",
      "score": "6-3 0-0 ret."
    },
    {
      "date": "20240203",
      "tournament": "Cordoba",
      "surface": "Hard",
      "level": "B",
      "round": "SF",
      "best_of": "3",
      "rank": "",
      "opp_rank": "",
      "result": "L",
      "opponent": "A. Collarini",
      "score": "6(5)-7(7) 1-6"
    },
    {
      "date": "20240123",
      "tournament": "Punta Del Este Challenger Men",
      "surface": "Hard",
      "level": "C",
      "round": "R32",
      "best_of": "3",
      "rank": "",
      "opp_rank": "",
      "result": "L",
      "opponent": "G. Mager",
      "score": "6-3 6(5)-7(7) 6(3)-7(7)"
    },
    {
      "date": "20230926",
      "tournament": "Braga Challenger Men",
      "surface": "Hard",
      "level": "C",
      "round": "R32",
      "best_of": "3",
      "rank": "",
      "opp_rank": "",
      "result": "L",
      "opponent": "O. Roca Batalla",
      "score": "6-3 6-3"
    },
    {
      "date": "20230907",
      "tournament": "Tulln Challenger Men",
      "surface": "Hard",
      "level": "C",
      "round": "R16",
      "best_of": "3",
      "rank": "",
      "opp_rank": "",
      "result": "L",
      "opponent": "S. Rodriguez Taverna",
      "score": "6(4)-7(7) 6-4 7(7)-6(4)"
    },
    {
      "date": "20230905",
      "tournament": "Tulln Challenger Men",
      "surface": "Hard",
      "level": "C",
      "round": "R32",
      "best_of": "3",
      "rank": "",
      "opp_rank": "",
      "result": "W",
      "opponent": "B. Hassan",
      "score": "7-5 6-4"
    },
    {
      "date": "20230604",
      "tournament": "Troisdorf",
      "surface": "Hard",
      "level": "C",
      "round": "F",
      "best_of": "3",
      "rank": "",
      "opp_rank": "",
      "result": "W",
      "opponent": "F. Ferreira Silva",
      "score": "6-2 5-7 6-3"
    },
    {
      "date": "20230603",
      "tournament": "Troisdorf",
      "surface": "Hard",
      "level": "C",
      "round": "SF",
      "best_of": "3",
      "rank": "",
      "opp_rank": "",
      "result": "W",
      "opponent": "P. Kotov",
      "score": "7(7)-6(5) 1-6 1-6"
    },
    {
      "date": "20230602",
      "tournament": "Troisdorf",
      "surface": "Hard",
      "level": "C",
      "round": "QF",
      "best_of": "3",
      "rank": "",
      "opp_rank": "",
      "result": "W",
      "opponent": "N. Hardt",
      "score": "3-6 7(7)-6(3) 7(7)-6(4)"
    },
    {
      "date": "20230531",
      "tournament": "Troisdorf",
      "surface": "Hard",
      "level": "C",
      "round": "R16",
      "best_of": "3",
      "rank": "",
      "opp_rank": "",
      "result": "W",
      "opponent": "L. Klein",
      "score": "4-6 2-6"
    },
    {
      "date": "20230530",
      "tournament": "Troisdorf",
      "surface": "Hard",
      "level": "C",
      "round": "R32",
      "best_of": "3",
      "rank": "",
      "opp_rank": "",
      "result": "W",
      "opponent": "O. Roca Batalla",
      "score": "6-2 6-0"
    },
    {
      "date": "20230515",
      "tournament": "Oeiras 4 Challenger Men",
      "surface": "Hard",
      "level": "C",
      "round": "R32",
      "best_of": "3",
      "rank": "",
      "opp_rank": "",
      "result": "L",
      "opponent": "H. Dellien",
      "score": "1-6 3-6"
    },
    {
      "date": "20230406",
      "tournament": "Murcia Challenger Men",
      "surface": "Hard",
      "level": "C",
      "round": "R16",
      "best_of": "3",
      "rank": "",
      "opp_rank": "",
      "result": "L",
      "opponent": "B. Gojo",
      "score": "6(6)-7(8) 6-3 6(5)-7(7)"
    },
    {
      "date": "20230404",
      "tournament": "Murcia Challenger Men",
      "surface": "Hard",
      "level": "C",
      "round": "R32",
      "best_of": "3",
      "rank": "",
      "opp_rank": "",
      "result": "W",
      "opponent": "M. Landaluce",
      "score": "7(7)-6(4) 6-4"
    },
    {
      "date": "20230306",
      "tournament": "Antalya",
      "surface": "Hard",
      "level": "C",
      "round": "R32",
      "best_of": "3",
      "rank": "",
      "opp_rank": "",
      "result": "L",
      "opponent": "N. Fatic",
      "score": "7-5 6-3"
    },
    {
      "date": "20221202",
      "tournament": "Maia",
      "surface": "Hard",
      "level": "C",
      "round": "QF",
      "best_of": "3",
      "rank": "",
      "opp_rank": "",
      "result": "L",
      "opponent": "L. van Assche",
      "score": "6-1 6-2"
    },
    {
      "date": "20221130",
      "tournament": "Maia",
      "surface": "Hard",
      "level": "C",
      "round": "R16",
      "best_of": "3",
      "rank": "",
      "opp_rank": "",
      "result": "W",
      "opponent": "A. Collarini",
      "score": "4-6 7-5 0-0 ret."
    },
    {
      "date": "20221129",
      "tournament": "Maia",
      "surface": "Hard",
      "level": "C",
      "round": "R32",
      "best_of": "3",
      "rank": "",
      "opp_rank": "",
      "result": "W",
      "opponent": "L. Darderi",
      "score": "3-6 4-6"
    },
    {
      "date": "20221110",
      "tournament": "M15 Benicarlo",
      "surface": "Hard",
      "level": "I",
      "round": "R16",
      "best_of": "3",
      "rank": "",
      "opp_rank": "",
      "result": "L",
      "opponent": "A. Reymond",
      "score": "6-4 6-4"
    },
    {
      "date": "20221109",
      "tournament": "M15 Benicarlo",
      "surface": "Hard",
      "level": "I",
      "round": "R32",
      "best_of": "3",
      "rank": "",
      "opp_rank": "",
      "result": "W",
      "opponent": "J. Domenech Castillo",
      "score": "6-2 6-1"
    },
    {
      "date": "20220907",
      "tournament": "Tulln",
      "surface": "Hard",
      "level": "C",
      "round": "R16",
      "best_of": "3",
      "rank": "",
      "opp_rank": "",
      "result": "L",
      "opponent": "J. Kovalik",
      "score": "6-3 4-0 ret."
    },
    {
      "date": "20220906",
      "tournament": "Tulln",
      "surface": "Hard",
      "level": "C",
      "round": "R32",
      "best_of": "3",
      "rank": "",
      "opp_rank": "",
      "result": "W",
      "opponent": "G. Melzer",
      "score": "6-2 7-5"
    },
    {
      "date": "20220905",
      "tournament": "Tulln",
      "surface": "Hard",
      "level": "C",
      "round": "F",
      "best_of": "3",
      "rank": "",
      "opp_rank": "",
      "result": "W",
      "opponent": "F. Horansky",
      "score": "4-6 6-0 2-6"
    },
    {
      "date": "20220904",
      "tournament": "Tulln",
      "surface": "Hard",
      "level": "C",
      "round": "SF",
      "best_of": "3",
      "rank": "",
      "opp_rank": "",
      "result": "W",
      "opponent": "M. Krumich",
      "score": "3-6 6-3 6(7)-7(9)"
    },
    {
      "date": "20220804",
      "tournament": "M25 Bolzano",
      "surface": "Hard",
      "level": "I",
      "round": "QF",
      "best_of": "3",
      "rank": "",
      "opp_rank": "",
      "result": "L",
      "opponent": "F. Forti",
      "score": "7(7)-6(4) 3-6 6-4"
    },
    {
      "date": "20220803",
      "tournament": "M25 Bolzano",
      "surface": "Hard",
      "level": "I",
      "round": "R16",
      "best_of": "3",
      "rank": "",
      "opp_rank": "",
      "result": "W",
      "opponent": "H. Rieder",
      "score": "6-4 6-2"
    },
    {
      "date": "20220802",
      "tournament": "M25 Bolzano",
      "surface": "Hard",
      "level": "I",
      "round": "R32",
      "best_of": "3",
      "rank": "",
      "opp_rank": "",
      "result": "W",
      "opponent": "C. Fossati",
      "score": "2-6 6-1 6-3"
    },
    {
      "date": "20220716",
      "tournament": "Amersfoort",
      "surface": "Hard",
      "level": "C",
      "round": "SF",
      "best_of": "3",
      "rank": "",
      "opp_rank": "",
      "result": "L",
      "opponent": "T. Griekspoor",
      "score": "2-6 6-3 3-6"
    },
    {
      "date": "20220715",
      "tournament": "Amersfoort",
      "surface": "Hard",
      "level": "C",
      "round": "QF",
      "best_of": "3",
      "rank": "",
      "opp_rank": "",
      "result": "W",
      "opponent": "M. Houkes",
      "score": "2-6 7(7)-6(4) 6(5)-7(7)"
    },
    {
      "date": "20220713",
      "tournament": "Amersfoort",
      "surface": "Hard",
      "level": "C",
      "round": "R16",
      "best_of": "3",
      "rank": "",
      "opp_rank": "",
      "result": "W",
      "opponent": "A. Fils",
      "score": "6-3 6-1"
    },
    {
      "date": "20220712",
      "tournament": "Amersfoort",
      "surface": "Hard",
      "level": "C",
      "round": "R32",
      "best_of": "3",
      "rank": "",
      "opp_rank": "",
      "result": "W",
      "opponent": "D. Wassermann",
      "score": "6-4 7(7)-6(3)"
    },
    {
      "date": "20220711",
      "tournament": "Amersfoort",
      "surface": "Hard",
      "level": "C",
      "round": "F",
      "best_of": "3",
      "rank": "",
      "opp_rank": "",
      "result": "W",
      "opponent": "S. Pontjodikromo",
      "score": "6-2 5-7 6-2"
    },
    {
      "date": "20220710",
      "tournament": "Amersfoort",
      "surface": "Hard",
      "level": "C",
      "round": "SF",
      "best_of": "3",
      "rank": "",
      "opp_rank": "",
      "result": "W",
      "opponent": "S. Verbeek",
      "score": "7(7)-6(3) 7(8)-6(6)"
    },
    {
      "date": "20220705",
      "tournament": "Salzburg",
      "surface": "Hard",
      "level": "C",
      "round": "R32",
      "best_of": "3",
      "rank": "",
      "opp_rank": "",
      "result": "L",
      "opponent": "D. Novak",
      "score": "2-6 5-7"
    },
    {
      "date": "20220704",
      "tournament": "Salzburg",
      "surface": "Hard",
      "level": "C",
      "round": "F",
      "best_of": "3",
      "rank": "",
      "opp_rank": "",
      "result": "W",
      "opponent": "P. Martin Tiffon",
      "score": "6(3)-7(7) 1-6"
    },
    {
      "date": "20220703",
      "tournament": "Salzburg",
      "surface": "Hard",
      "level": "C",
      "round": "SF",
      "best_of": "3",
      "rank": "",
      "opp_rank": "",
      "result": "W",
      "opponent": "P. Goldsteiner",
      "score": "4-6 1-6"
    },
    {
      "date": "20220620",
      "tournament": "Oeiras 3",
      "surface": "Hard",
      "level": "C",
      "round": "F",
      "best_of": "3",
      "rank": "",
      "opp_rank": "",
      "result": "L",
      "opponent": "A. Lazarov",
      "score": "6-1 6(6)-7(8) 7(7)-6(1)"
    },
    {
      "date": "20220619",
      "tournament": "Oeiras 3",
      "surface": "Hard",
      "level": "C",
      "round": "SF",
      "best_of": "3",
      "rank": "",
      "opp_rank": "",
      "result": "W",
      "opponent": "D. Poljak",
      "score": "3-6 7(7)-6(2) 7(7)-6(4)"
    },
    {
      "date": "20220524",
      "tournament": "M25 Mataro",
      "surface": "Hard",
      "level": "I",
      "round": "R32",
      "best_of": "3",
      "rank": "",
      "opp_rank": "",
      "result": "L",
      "opponent": "N. Hardt",
      "score": "6-2 1-6 6-3"
    },
    {
      "date": "20220518",
      "tournament": "Shymkent 2",
      "surface": "Hard",
      "level": "C",
      "round": "R16",
      "best_of": "3",
      "rank": "",
      "opp_rank": "",
      "result": "L",
      "opponent": "E. Karlovskiy",
      "score": "7(7)-6(5) 7-5"
    },
    {
      "date": "20220517",
      "tournament": "Shymkent 2",
      "surface": "Hard",
      "level": "C",
      "round": "R32",
      "best_of": "3",
      "rank": "",
      "opp_rank": "",
      "result": "W",
      "opponent": "V. Durasovic",
      "score": "3-6 6-3 3-6"
    },
    {
      "date": "20220516",
      "tournament": "Shymkent 2",
      "surface": "Hard",
      "level": "C",
      "round": "F",
      "best_of": "3",
      "rank": "",
      "opp_rank": "",
      "result": "W",
      "opponent": "Pe. Tsitsipas",
      "score": "6-1 7-5"
    },
    {
      "date": "20220429",
      "tournament": "M15 Shymkent 2",
      "surface": "Hard",
      "level": "I",
      "round": "QF",
      "best_of": "3",
      "rank": "",
      "opp_rank": "",
      "result": "L",
      "opponent": "S. Cuenin",
      "score": "2-6 6-2 4-6"
    },
    {
      "date": "20220428",
      "tournament": "M15 Shymkent 2",
      "surface": "Hard",
      "level": "I",
      "round": "R16",
      "best_of": "3",
      "rank": "",
      "opp_rank": "",
      "result": "W",
      "opponent": "Z. Tkemaladze",
      "score": "3-6 6(5)-7(7)"
    },
    {
      "date": "20220427",
      "tournament": "M15 Shymkent 2",
      "surface": "Hard",
      "level": "I",
      "round": "R32",
      "best_of": "3",
      "rank": "",
      "opp_rank": "",
      "result": "W",
      "opponent": "A. Lobanov",
      "score": "1-6 3-6"
    },
    {
      "date": "20220424",
      "tournament": "M15 Shymkent",
      "surface": "Hard",
      "level": "I",
      "round": "F",
      "best_of": "3",
      "rank": "",
      "opp_rank": "",
      "result": "W",
      "opponent": "E. Vanshelboim",
      "score": "6-3 6-4"
    },
    {
      "date": "20220423",
      "tournament": "M15 Shymkent",
      "surface": "Hard",
      "level": "I",
      "round": "SF",
      "best_of": "3",
      "rank": "",
      "opp_rank": "",
      "result": "W",
      "opponent": "A. Kachmazov",
      "score": "6-2 6-2"
    },
    {
      "date": "20220422",
      "tournament": "M15 Shymkent",
      "surface": "Hard",
      "level": "I",
      "round": "QF",
      "best_of": "3",
      "rank": "",
      "opp_rank": "",
      "result": "W",
      "opponent": "M. Martinez",
      "score": "6-3 6-4"
    },
    {
      "date": "20220421",
      "tournament": "M15 Shymkent",
      "surface": "Hard",
      "level": "I",
      "round": "R16",
      "best_of": "3",
      "rank": "",
      "opp_rank": "",
      "result": "W",
      "opponent": "M. Borisiouk",
      "score": "6-2 6-1"
    },
    {
      "date": "20220420",
      "tournament": "M15 Shymkent",
      "surface": "Hard",
      "level": "I",
      "round": "R32",
      "best_of": "3",
      "rank": "",
      "opp_rank": "",
      "result": "W",
      "opponent": "L. Rottoli",
      "score": "7(7)-6(5) 7-5"
    },
    {
      "date": "20220409",
      "tournament": "Murcia",
      "surface": "Hard",
      "level": "C",
      "round": "SF",
      "best_of": "3",
      "rank": "",
      "opp_rank": "",
      "result": "L",
      "opponent": "C. H. Tseng",
      "score": "4-6 4-6"
    },
    {
      "date": "20220408",
      "tournament": "Murcia",
      "surface": "Hard",
      "level": "C",
      "round": "QF",
      "best_of": "3",
      "rank": "",
      "opp_rank": "",
      "result": "W",
      "opponent": "J. Forejtek",
      "score": "6(5)-7(7) 6-4 5-7"
    },
    {
      "date": "20220407",
      "tournament": "Murcia",
      "surface": "Hard",
      "level": "C",
      "round": "R16",
      "best_of": "3",
      "rank": "",
      "opp_rank": "",
      "result": "W",
      "opponent": "L. Giustino",
      "score": "4-6 3-6"
    },
    {
      "date": "20220406",
      "tournament": "Murcia",
      "surface": "Hard",
      "level": "C",
      "round": "R32",
      "best_of": "3",
      "rank": "",
      "opp_rank": "",
      "result": "W",
      "opponent": "J. M. Cerundolo",
      "score": "3-6 7(7)-6(3) 2-0 ret."
    },
    {
      "date": "20220401",
      "tournament": "M15 Antalya 8",
      "surface": "Hard",
      "level": "I",
      "round": "QF",
      "best_of": "3",
      "rank": "",
      "opp_rank": "",
      "result": "L",
      "opponent": "T. Stodder",
      "score": "4-6 4-6"
    },
    {
      "date": "20220331",
      "tournament": "M15 Antalya 8",
      "surface": "Hard",
      "level": "I",
      "round": "R16",
      "best_of": "3",
      "rank": "",
      "opp_rank": "",
      "result": "W",
      "opponent": "R. Kawakami",
      "score": "4-6 4-6"
    },
    {
      "date": "20220329",
      "tournament": "M15 Antalya 8",
      "surface": "Hard",
      "level": "I",
      "round": "R32",
      "best_of": "3",
      "rank": "",
      "opp_rank": "",
      "result": "W",
      "opponent": "D. A. Tomescu",
      "score": "4-6 6(7)-7(9)"
    },
    {
      "date": "20220325",
      "tournament": "M15 Antalya 7",
      "surface": "Hard",
      "level": "I",
      "round": "QF",
      "best_of": "3",
      "rank": "",
      "opp_rank": "",
      "result": "L",
      "opponent": "M. Houkes",
      "score": "6-4 6(9)-7(11) 7-5"
    },
    {
      "date": "20220324",
      "tournament": "M15 Antalya 7",
      "surface": "Hard",
      "level": "I",
      "round": "R16",
      "best_of": "3",
      "rank": "",
      "opp_rank": "",
      "result": "W",
      "opponent": "K. Kirci",
      "score": "6-2 7(7)-6(2)"
    },
    {
      "date": "20220322",
      "tournament": "M15 Antalya 7",
      "surface": "Hard",
      "level": "I",
      "round": "R32",
      "best_of": "3",
      "rank": "",
      "opp_rank": "",
      "result": "W",
      "opponent": "D. A. Tomescu",
      "score": "6-3 7-5"
    },
    {
      "date": "20220315",
      "tournament": "M25 Antalya 4",
      "surface": "Hard",
      "level": "I",
      "round": "R32",
      "best_of": "3",
      "rank": "",
      "opp_rank": "",
      "result": "L",
      "opponent": "S. Polukhin",
      "score": "2-6 4-6"
    },
    {
      "date": "20220302",
      "tournament": "M25 Nur-Sultan 2",
      "surface": "Hard",
      "level": "I",
      "round": "R32",
      "best_of": "3",
      "rank": "",
      "opp_rank": "",
      "result": "L",
      "opponent": "A. Dubrivnyy",
      "score": "6-4 7-5"
    },
    {
      "date": "20220222",
      "tournament": "ITF M25 Nur-Sultan Men",
      "surface": "Hard",
      "level": "I",
      "round": "R32",
      "best_of": "3",
      "rank": "",
      "opp_rank": "",
      "result": "L",
      "opponent": "B. Zhukayev",
      "score": "3-6 6-2 5-7"
    },
    {
      "date": "20220222",
      "tournament": "M25 Nur-Sultan",
      "surface": "Hard",
      "level": "I",
      "round": "R32",
      "best_of": "3",
      "rank": "",
      "opp_rank": "",
      "result": "L",
      "opponent": "B. Zhukayev",
      "score": "3-6 6-2 5-7"
    },
    {
      "date": "20220201",
      "tournament": "M15 Monastir 4",
      "surface": "Hard",
      "level": "I",
      "round": "R32",
      "best_of": "3",
      "rank": "",
      "opp_rank": "",
      "result": "L",
      "opponent": "A. Reymond",
      "score": "6-2 6-0"
    },
    {
      "date": "20220127",
      "tournament": "M15 Monastir 3",
      "surface": "Hard",
      "level": "I",
      "round": "R16",
      "best_of": "3",
      "rank": "",
      "opp_rank": "",
      "result": "L",
      "opponent": "M. H. Rehberg",
      "score": "2-6 3-6"
    },
    {
      "date": "20220125",
      "tournament": "M15 Monastir 3",
      "surface": "Hard",
      "level": "I",
      "round": "R32",
      "best_of": "3",
      "rank": "",
      "opp_rank": "",
      "result": "W",
      "opponent": "K. Kivattsev",
      "score": "4-6 5-7"
    },
    {
      "date": "20211213",
      "tournament": "Maia 2",
      "surface": "Hard",
      "level": "C",
      "round": "F",
      "best_of": "3",
      "rank": "",
      "opp_rank": "",
      "result": "L",
      "opponent": "E. Lavagno",
      "score": "6-1 3-6 6-2"
    },
    {
      "date": "20211212",
      "tournament": "Maia 2",
      "surface": "Hard",
      "level": "C",
      "round": "SF",
      "best_of": "3",
      "rank": "",
      "opp_rank": "",
      "result": "W",
      "opponent": "L. Bocchi",
      "score": "6-2 6-4"
    },
    {
      "date": "20211207",
      "tournament": "Maia Challenger Men",
      "surface": "Hard",
      "level": "C",
      "round": "R32",
      "best_of": "3",
      "rank": "",
      "opp_rank": "",
      "result": "L",
      "opponent": "A. Dougaz",
      "score": "1-6 4-6"
    },
    {
      "date": "20211129",
      "tournament": "Antalya 3",
      "surface": "Hard",
      "level": "C",
      "round": "SF",
      "best_of": "3",
      "rank": "",
      "opp_rank": "",
      "result": "L",
      "opponent": "L. Wessels",
      "score": "6-2 6(3)-7(7) 0-3 ret."
    },
    {
      "date": "20211121",
      "tournament": "Manama Challenger Men",
      "surface": "Hard",
      "level": "C",
      "round": "SF",
      "best_of": "3",
      "rank": "",
      "opp_rank": "",
      "result": "L",
      "opponent": "M. Neuchrist",
      "score": "6(6)-7(8) 4-6"
    },
    {
      "date": "20211114",
      "tournament": "ITF M15 Benicarlo Men",
      "surface": "Hard",
      "level": "I",
      "round": "F",
      "best_of": "3",
      "rank": "",
      "opp_rank": "",
      "result": "L",
      "opponent": "P. Llamas Ruiz",
      "score": "6-4 6-4"
    },
    {
      "date": "20211113",
      "tournament": "ITF M15 Benicarlo Men",
      "surface": "Hard",
      "level": "I",
      "round": "SF",
      "best_of": "3",
      "rank": "",
      "opp_rank": "",
      "result": "W",
      "opponent": "C. Sanchez Jover",
      "score": "4-6 2-6"
    },
    {
      "date": "20211112",
      "tournament": "ITF M15 Benicarlo Men",
      "surface": "Hard",
      "level": "I",
      "round": "QF",
      "best_of": "3",
      "rank": "",
      "opp_rank": "",
      "result": "W",
      "opponent": "I. Lopez Morillo",
      "score": "6-4 3-6 6-1"
    },
    {
      "date": "20211111",
      "tournament": "ITF M15 Benicarlo Men",
      "surface": "Hard",
      "level": "I",
      "round": "R16",
      "best_of": "3",
      "rank": "",
      "opp_rank": "",
      "result": "W",
      "opponent": "F. E. Egea",
      "score": "6-3 7(7)-6(4)"
    },
    {
      "date": "20211109",
      "tournament": "ITF M15 Benicarlo Men",
      "surface": "Hard",
      "level": "I",
      "round": "R32",
      "best_of": "3",
      "rank": "",
      "opp_rank": "",
      "result": "W",
      "opponent": "E. Butvilas",
      "score": "6-4 4-6 6-0"
    },
    {
      "date": "20211022",
      "tournament": "M15 Girona",
      "surface": "Hard",
      "level": "I",
      "round": "QF",
      "best_of": "3",
      "rank": "",
      "opp_rank": "",
      "result": "L",
      "opponent": "M. Kasnikowski",
      "score": "4-6 7-5 7-5"
    },
    {
      "date": "20211021",
      "tournament": "M15 Girona",
      "surface": "Hard",
      "level": "I",
      "round": "R16",
      "best_of": "3",
      "rank": "",
      "opp_rank": "",
      "result": "W",
      "opponent": "A. Moro Canas",
      "score": "7(8)-6(6) 6-2"
    },
    {
      "date": "20211019",
      "tournament": "M15 Girona",
      "surface": "Hard",
      "level": "I",
      "round": "R32",
      "best_of": "3",
      "rank": "",
      "opp_rank": "",
      "result": "W",
      "opponent": "A. Manzanera Pertusa",
      "score": "6-1 6(3)-7(7) 7(7)-6(3)"
    },
    {
      "date": "20211014",
      "tournament": "M15 Platja D'Aro 2",
      "surface": "Hard",
      "level": "I",
      "round": "R16",
      "best_of": "3",
      "rank": "",
      "opp_rank": "",
      "result": "L",
      "opponent": "M. Damas",
      "score": "6-2 4-6 6-1"
    },
    {
      "date": "20211013",
      "tournament": "M15 Platja D'Aro 2",
      "surface": "Hard",
      "level": "I",
      "round": "R32",
      "best_of": "3",
      "rank": "",
      "opp_rank": "",
      "result": "W",
      "opponent": "F. E. Egea",
      "score": "6-4 6(5)-7(7) 6-3"
    },
    {
      "date": "20211010",
      "tournament": "M15 Platja D'Aro",
      "surface": "Hard",
      "level": "I",
      "round": "F",
      "best_of": "3",
      "rank": "",
      "opp_rank": "",
      "result": "W",
      "opponent": "J. F. Vidal Azorin",
      "score": "4-6 7-5 2-6"
    },
    {
      "date": "20211009",
      "tournament": "M15 Platja D'Aro",
      "surface": "Hard",
      "level": "I",
      "round": "SF",
      "best_of": "3",
      "rank": "",
      "opp_rank": "",
      "result": "W",
      "opponent": "B. P. Toledo",
      "score": "3-6 2-3 ret."
    },
    {
      "date": "20211008",
      "tournament": "M15 Platja D'Aro",
      "surface": "Hard",
      "level": "I",
      "round": "QF",
      "best_of": "3",
      "rank": "",
      "opp_rank": "",
      "result": "W",
      "opponent": "G. Den Heijer",
      "score": "5-7 4-6"
    },
    {
      "date": "20211007",
      "tournament": "M15 Platja D'Aro",
      "surface": "Hard",
      "level": "I",
      "round": "R16",
      "best_of": "3",
      "rank": "",
      "opp_rank": "",
      "result": "W",
      "opponent": "M. Navone",
      "score": "6(4)-7(7) 3-6"
    },
    {
      "date": "20211006",
      "tournament": "M15 Platja D'Aro",
      "surface": "Hard",
      "level": "I",
      "round": "R32",
      "best_of": "3",
      "rank": "",
      "opp_rank": "",
      "result": "W",
      "opponent": "F. Andreu Garcia",
      "score": "6-3 3-6 1-6"
    },
    {
      "date": "20210921",
      "tournament": "Bucharest",
      "surface": "Hard",
      "level": "C",
      "round": "R32",
      "best_of": "3",
      "rank": "",
      "opp_rank": "",
      "result": "L",
      "opponent": "F. Cobolli",
      "score": "5-7 7(8)-6(6) 1-6"
    },
    {
      "date": "20210920",
      "tournament": "Bucharest",
      "surface": "Hard",
      "level": "C",
      "round": "F",
      "best_of": "3",
      "rank": "",
      "opp_rank": "",
      "result": "W",
      "opponent": "U. Ignatik",
      "score": "0-6 6-2 6-3"
    },
    {
      "date": "20210919",
      "tournament": "Bucharest",
      "surface": "Hard",
      "level": "C",
      "round": "SF",
      "best_of": "3",
      "rank": "",
      "opp_rank": "",
      "result": "W",
      "opponent": "F. Forti",
      "score": "6(2)-7(7) 3-6"
    },
    {
      "date": "20210907",
      "tournament": "Kyiv",
      "surface": "Hard",
      "level": "C",
      "round": "R32",
      "best_of": "3",
      "rank": "",
      "opp_rank": "",
      "result": "L",
      "opponent": "F. Forti",
      "score": "6-1 3-6 6-1"
    },
    {
      "date": "20210906",
      "tournament": "Kyiv",
      "surface": "Hard",
      "level": "C",
      "round": "F",
      "best_of": "3",
      "rank": "",
      "opp_rank": "",
      "result": "W",
      "opponent": "D. Kalenichenko",
      "score": "4-6 2-6"
    },
    {
      "date": "20210905",
      "tournament": "Kyiv",
      "surface": "Hard",
      "level": "C",
      "round": "SF",
      "best_of": "3",
      "rank": "",
      "opp_rank": "",
      "result": "W",
      "opponent": "V. Manafov",
      "score": "2-6 4-6"
    },
    {
      "date": "20210831",
      "tournament": "ITF M25 Oviedo Men",
      "surface": "Hard",
      "level": "I",
      "round": "R32",
      "best_of": "3",
      "rank": "",
      "opp_rank": "",
      "result": "L",
      "opponent": "P. Llamas Ruiz",
      "score": "1-6 6-3 5-7"
    },
    {
      "date": "20210826",
      "tournament": "ITF M25 Santander Men",
      "surface": "Hard",
      "level": "I",
      "round": "R16",
      "best_of": "3",
      "rank": "",
      "opp_rank": "",
      "result": "L",
      "opponent": "A. Marti Pujolras",
      "score": "6-4 6-3"
    },
    {
      "date": "20210825",
      "tournament": "ITF M25 Santander Men",
      "surface": "Hard",
      "level": "I",
      "round": "R32",
      "best_of": "3",
      "rank": "",
      "opp_rank": "",
      "result": "W",
      "opponent": "J. C. Porras",
      "score": "6-0 6-0"
    },
    {
      "date": "20210820",
      "tournament": "ITF M25 Koksijde Men",
      "surface": "Hard",
      "level": "I",
      "round": "QF",
      "best_of": "3",
      "rank": "",
      "opp_rank": "",
      "result": "L",
      "opponent": "J. De Loore",
      "score": "4-6 3-6"
    },
    {
      "date": "20210819",
      "tournament": "ITF M25 Koksijde Men",
      "surface": "Hard",
      "level": "I",
      "round": "R16",
      "best_of": "3",
      "rank": "",
      "opp_rank": "",
      "result": "W",
      "opponent": "F. Passaro",
      "score": "0-6 0-6"
    },
    {
      "date": "20210817",
      "tournament": "ITF M25 Koksijde Men",
      "surface": "Hard",
      "level": "I",
      "round": "R32",
      "best_of": "3",
      "rank": "",
      "opp_rank": "",
      "result": "W",
      "opponent": "A. Aubriot",
      "score": "2-6 6-2 2-6"
    },
    {
      "date": "20210729",
      "tournament": "ITF M25 Denia Men",
      "surface": "Hard",
      "level": "I",
      "round": "R16",
      "best_of": "3",
      "rank": "",
      "opp_rank": "",
      "result": "L",
      "opponent": "L. E. Esteve",
      "score": "6-1 6-4"
    },
    {
      "date": "20210728",
      "tournament": "ITF M25 Denia Men",
      "surface": "Hard",
      "level": "I",
      "round": "R32",
      "best_of": "3",
      "rank": "",
      "opp_rank": "",
      "result": "W",
      "opponent": "G. Kravchenko",
      "score": "6-3 0-6 6-1"
    },
    {
      "date": "20210630",
      "tournament": "ITF M25 Belgrade Men",
      "surface": "Hard",
      "level": "I",
      "round": "R32",
      "best_of": "3",
      "rank": "",
      "opp_rank": "",
      "result": "L",
      "opponent": "F. Marozsan",
      "score": "2-6 1-6"
    },
    {
      "date": "20210613",
      "tournament": "Almaty 2",
      "surface": "Hard",
      "level": "C",
      "round": "SF",
      "best_of": "3",
      "rank": "",
      "opp_rank": "",
      "result": "L",
      "opponent": "V. Orlov",
      "score": "7(7)-6(4) 7(7)-6(4)"
    },
    {
      "date": "20210605",
      "tournament": "M15 Shymkent 4",
      "surface": "Hard",
      "level": "I",
      "round": "SF",
      "best_of": "3",
      "rank": "",
      "opp_rank": "",
      "result": "L",
      "opponent": "Y. Bondarevskiy",
      "score": "6(2)-7(7) 4-6"
    },
    {
      "date": "20210604",
      "tournament": "M15 Shymkent 4",
      "surface": "Hard",
      "level": "I",
      "round": "QF",
      "best_of": "3",
      "rank": "",
      "opp_rank": "",
      "result": "W",
      "opponent": "A. Shevchenko",
      "score": "7-5 6-4"
    },
    {
      "date": "20210603",
      "tournament": "M15 Shymkent 4",
      "surface": "Hard",
      "level": "I",
      "round": "R16",
      "best_of": "3",
      "rank": "",
      "opp_rank": "",
      "result": "W",
      "opponent": "A. Binda",
      "score": "6-2 6-2"
    },
    {
      "date": "20210602",
      "tournament": "M15 Shymkent 4",
      "surface": "Hard",
      "level": "I",
      "round": "R32",
      "best_of": "3",
      "rank": "",
      "opp_rank": "",
      "result": "W",
      "opponent": "A. Chepelev",
      "score": "6-2 6-4"
    },
    {
      "date": "20210528",
      "tournament": "ITF M15 Shymkent 2 Men",
      "surface": "Hard",
      "level": "I",
      "round": "QF",
      "best_of": "3",
      "rank": "",
      "opp_rank": "",
      "result": "L",
      "opponent": "A. Shevchenko",
      "score": "6-3 6(3)-7(7) 0-6"
    },
    {
      "date": "20210528",
      "tournament": "M15 Shymkent 3",
      "surface": "Hard",
      "level": "I",
      "round": "QF",
      "best_of": "3",
      "rank": "",
      "opp_rank": "",
      "result": "L",
      "opponent": "A. Shevchenko",
      "score": "6-3 6(3)-7(7) 0-6"
    },
    {
      "date": "20210527",
      "tournament": "ITF M15 Shymkent 2 Men",
      "surface": "Hard",
      "level": "I",
      "round": "R16",
      "best_of": "3",
      "rank": "",
      "opp_rank": "",
      "result": "W",
      "opponent": "E. Philippov",
      "score": "3-6 3-6"
    },
    {
      "date": "20210527",
      "tournament": "M15 Shymkent 3",
      "surface": "Hard",
      "level": "I",
      "round": "R16",
      "best_of": "3",
      "rank": "",
      "opp_rank": "",
      "result": "W",
      "opponent": "E. Philippov",
      "score": "3-6 3-6"
    },
    {
      "date": "20210526",
      "tournament": "ITF M15 Shymkent 2 Men",
      "surface": "Hard",
      "level": "I",
      "round": "R32",
      "best_of": "3",
      "rank": "",
      "opp_rank": "",
      "result": "W",
      "opponent": "R. Nashatyrkin",
      "score": "1-6 4-6"
    },
    {
      "date": "20210526",
      "tournament": "M15 Shymkent 3",
      "surface": "Hard",
      "level": "I",
      "round": "R32",
      "best_of": "3",
      "rank": "",
      "opp_rank": "",
      "result": "W",
      "opponent": "R. Nashatyrkin",
      "score": "1-6 4-6"
    },
    {
      "date": "20210513",
      "tournament": "ITF M15 Valldoreix Men",
      "surface": "Hard",
      "level": "I",
      "round": "R16",
      "best_of": "3",
      "rank": "",
      "opp_rank": "",
      "result": "L",
      "opponent": "M. Cuevas",
      "score": "2-6 7-5 3-6"
    },
    {
      "date": "20210512",
      "tournament": "ITF M15 Valldoreix Men",
      "surface": "Hard",
      "level": "I",
      "round": "R32",
      "best_of": "3",
      "rank": "",
      "opp_rank": "",
      "result": "W",
      "opponent": "B. Kuzuhara",
      "score": "6-3 4-6 1-6"
    },
    {
      "date": "20210505",
      "tournament": "M15 Majadahonda",
      "surface": "Hard",
      "level": "I",
      "round": "R32",
      "best_of": "3",
      "rank": "",
      "opp_rank": "",
      "result": "L",
      "opponent": "K. Jacquet",
      "score": "4-6 3-6"
    },
    {
      "date": "20210418",
      "tournament": "ITF M15 Shymkent Men",
      "surface": "Hard",
      "level": "I",
      "round": "F",
      "best_of": "3",
      "rank": "",
      "opp_rank": "",
      "result": "L",
      "opponent": "E. Vanshelboim",
      "score": "1-6 1-6"
    },
    {
      "date": "20210417",
      "tournament": "ITF M15 Shymkent Men",
      "surface": "Hard",
      "level": "I",
      "round": "SF",
      "best_of": "3",
      "rank": "",
      "opp_rank": "",
      "result": "W",
      "opponent": "J. F. Vidal Azorin",
      "score": "6-4 5-7 5-7"
    },
    {
      "date": "20210416",
      "tournament": "ITF M15 Shymkent Men",
      "surface": "Hard",
      "level": "I",
      "round": "QF",
      "best_of": "3",
      "rank": "",
      "opp_rank": "",
      "result": "W",
      "opponent": "L. Tomasetto",
      "score": "1-6 6-2 4-6"
    },
    {
      "date": "20210415",
      "tournament": "ITF M15 Shymkent Men",
      "surface": "Hard",
      "level": "I",
      "round": "R16",
      "best_of": "3",
      "rank": "",
      "opp_rank": "",
      "result": "W",
      "opponent": "D. Klok",
      "score": "5-7 6(4)-7(7)"
    },
    {
      "date": "20210414",
      "tournament": "ITF M15 Shymkent Men",
      "surface": "Hard",
      "level": "I",
      "round": "R32",
      "best_of": "3",
      "rank": "",
      "opp_rank": "",
      "result": "W",
      "opponent": "I. Liutarevich",
      "score": "2-6 4-6"
    },
    {
      "date": "20210411",
      "tournament": "ITF M15 Shymkent Men",
      "surface": "Hard",
      "level": "I",
      "round": "F",
      "best_of": "3",
      "rank": "",
      "opp_rank": "",
      "result": "W",
      "opponent": "E. Vanshelboim",
      "score": "3-6 7-5 5-7"
    },
    {
      "date": "20210410",
      "tournament": "ITF M15 Shymkent Men",
      "surface": "Hard",
      "level": "I",
      "round": "SF",
      "best_of": "3",
      "rank": "",
      "opp_rank": "",
      "result": "W",
      "opponent": "A. Campo",
      "score": "6-3 1-6 2-6"
    },
    {
      "date": "20210409",
      "tournament": "ITF M15 Shymkent Men",
      "surface": "Hard",
      "level": "I",
      "round": "QF",
      "best_of": "3",
      "rank": "",
      "opp_rank": "",
      "result": "W",
      "opponent": "D. Wenger",
      "score": "1-6 3-6"
    },
    {
      "date": "20210408",
      "tournament": "ITF M15 Shymkent Men",
      "surface": "Hard",
      "level": "I",
      "round": "R16",
      "best_of": "3",
      "rank": "",
      "opp_rank": "",
      "result": "W",
      "opponent": "J. Gibbens",
      "score": "3-6 3-6"
    },
    {
      "date": "20210407",
      "tournament": "ITF M15 Shymkent Men",
      "surface": "Hard",
      "level": "I",
      "round": "R32",
      "best_of": "3",
      "rank": "",
      "opp_rank": "",
      "result": "W",
      "opponent": "A. Ingarao",
      "score": "4-6 1-6"
    },
    {
      "date": "20210312",
      "tournament": "ITF M15 Kazan Men",
      "surface": "Hard",
      "level": "I",
      "round": "QF",
      "best_of": "3",
      "rank": "",
      "opp_rank": "",
      "result": "L",
      "opponent": "A. Kachmazov",
      "score": "6-3 6(3)-7(7) 6-3"
    },
    {
      "date": "20210311",
      "tournament": "ITF M15 Kazan Men",
      "surface": "Hard",
      "level": "I",
      "round": "R16",
      "best_of": "3",
      "rank": "",
      "opp_rank": "",
      "result": "W",
      "opponent": "D. Ibragimov",
      "score": "6-4 1-6 6-1"
    },
    {
      "date": "20210310",
      "tournament": "ITF M15 Kazan Men",
      "surface": "Hard",
      "level": "I",
      "round": "R32",
      "best_of": "3",
      "rank": "",
      "opp_rank": "",
      "result": "W",
      "opponent": "A. Khomich",
      "score": "6-4 6-4"
    },
    {
      "date": "20210302",
      "tournament": "St. Petersburg",
      "surface": "Hard",
      "level": "C",
      "round": "R32",
      "best_of": "3",
      "rank": "",
      "opp_rank": "",
      "result": "L",
      "opponent": "V. Kopriva",
      "score": "7-5 1-6 7(9)-6(7)"
    },
    {
      "date": "20210120",
      "tournament": "ITF M15 Cairo Men",
      "surface": "Hard",
      "level": "I",
      "round": "R32",
      "best_of": "3",
      "rank": "",
      "opp_rank": "",
      "result": "L",
      "opponent": "J. P. Paz",
      "score": "7(7)-6(4) 6-1"
    },
    {
      "date": "20210114",
      "tournament": "ITF M15 Cairo Men",
      "surface": "Hard",
      "level": "I",
      "round": "R16",
      "best_of": "3",
      "rank": "",
      "opp_rank": "",
      "result": "L",
      "opponent": "C. Sanchez Jover",
      "score": "6-3 6-4"
    },
    {
      "date": "20210113",
      "tournament": "ITF M15 Cairo Men",
      "surface": "Hard",
      "level": "I",
      "round": "R32",
      "best_of": "3",
      "rank": "",
      "opp_rank": "",
      "result": "W",
      "opponent": "Q. Folliot",
      "score": "4-6 6-3 6-2"
    },
    {
      "date": "20210105",
      "tournament": "ITF M15 Cairo Men",
      "surface": "Hard",
      "level": "I",
      "round": "R32",
      "best_of": "3",
      "rank": "",
      "opp_rank": "",
      "result": "L",
      "opponent": "L. Bocchi",
      "score": "3-6 6-1 6(0)-7(7)"
    },
    {
      "date": "20201209",
      "tournament": "ITF M15 Torello Men",
      "surface": "Hard",
      "level": "I",
      "round": "R32",
      "best_of": "3",
      "rank": "",
      "opp_rank": "",
      "result": "L",
      "opponent": "M. Bellucci",
      "score": "2-6 6(8)-7(10)"
    },
    {
      "date": "20201129",
      "tournament": "ITF M15 Benicarlo Men",
      "surface": "Hard",
      "level": "I",
      "round": "F",
      "best_of": "3",
      "rank": "",
      "opp_rank": "",
      "result": "L",
      "opponent": "N. Alvarez Varona",
      "score": "6(13)-7(15) 4-6"
    },
    {
      "date": "20201128",
      "tournament": "ITF M15 Benicarlo Men",
      "surface": "Hard",
      "level": "I",
      "round": "SF",
      "best_of": "3",
      "rank": "",
      "opp_rank": "",
      "result": "W",
      "opponent": "A. Cornut-Chauvinc",
      "score": "3-6 7(8)-6(6) 6-4"
    },
    {
      "date": "20201127",
      "tournament": "ITF M15 Benicarlo Men",
      "surface": "Hard",
      "level": "I",
      "round": "QF",
      "best_of": "3",
      "rank": "",
      "opp_rank": "",
      "result": "W",
      "opponent": "L. E. Esteve",
      "score": "4-6 6-0 4-6"
    },
    {
      "date": "20201126",
      "tournament": "ITF M15 Benicarlo Men",
      "surface": "Hard",
      "level": "I",
      "round": "R16",
      "best_of": "3",
      "rank": "",
      "opp_rank": "",
      "result": "W",
      "opponent": "L. van Assche",
      "score": "1-6 4-6"
    },
    {
      "date": "20201124",
      "tournament": "ITF M15 Benicarlo Men",
      "surface": "Hard",
      "level": "I",
      "round": "R32",
      "best_of": "3",
      "rank": "",
      "opp_rank": "",
      "result": "W",
      "opponent": "C. S. Perez",
      "score": "6-2 7(7)-6(2)"
    },
    {
      "date": "20201119",
      "tournament": "ITF M15 Villena Men",
      "surface": "Hard",
      "level": "I",
      "round": "R16",
      "best_of": "3",
      "rank": "",
      "opp_rank": "",
      "result": "L",
      "opponent": "N. Sanchez Izquierdo",
      "score": "3-6 6(4)-7(7)"
    },
    {
      "date": "20201117",
      "tournament": "ITF M15 Villena Men",
      "surface": "Hard",
      "level": "I",
      "round": "R32",
      "best_of": "3",
      "rank": "",
      "opp_rank": "",
      "result": "W",
      "opponent": "J. Nikles",
      "score": "6-4 6-3"
    },
    {
      "date": "20201112",
      "tournament": "ITF M15 Valldoreix Men",
      "surface": "Hard",
      "level": "I",
      "round": "R16",
      "best_of": "3",
      "rank": "",
      "opp_rank": "",
      "result": "L",
      "opponent": "H. Rune",
      "score": "0-6 1-6"
    },
    {
      "date": "20201111",
      "tournament": "ITF M15 Valldoreix Men",
      "surface": "Hard",
      "level": "I",
      "round": "R32",
      "best_of": "3",
      "rank": "",
      "opp_rank": "",
      "result": "W",
      "opponent": "A. Chepelev",
      "score": "6-1 1-6 6-4"
    },
    {
      "date": "20201022",
      "tournament": "ITF M15 Sharm El Sheikh Men",
      "surface": "Hard",
      "level": "I",
      "round": "R16",
      "best_of": "3",
      "rank": "",
      "opp_rank": "",
      "result": "L",
      "opponent": "F. Cobolli",
      "score": "1-6 0-4 ret."
    },
    {
      "date": "20201021",
      "tournament": "ITF M15 Sharm El Sheikh Men",
      "surface": "Hard",
      "level": "I",
      "round": "R32",
      "best_of": "3",
      "rank": "",
      "opp_rank": "",
      "result": "W",
      "opponent": "S. Rawat",
      "score": "7-5 7-5"
    },
    {
      "date": "20201015",
      "tournament": "ITF M15 Sharm El Sheikh Men",
      "surface": "Hard",
      "level": "I",
      "round": "R16",
      "best_of": "3",
      "rank": "",
      "opp_rank": "",
      "result": "L",
      "opponent": "G. Kravchenko",
      "score": "6-3 3-6 6(1)-7(7)"
    },
    {
      "date": "20201014",
      "tournament": "ITF M15 Sharm El Sheikh Men",
      "surface": "Hard",
      "level": "I",
      "round": "R32",
      "best_of": "3",
      "rank": "",
      "opp_rank": "",
      "result": "W",
      "opponent": "E. Noskin",
      "score": "4-6 6(3)-7(7)"
    },
    {
      "date": "20200904",
      "tournament": "M15 Novomoskovsk",
      "surface": "Hard",
      "level": "I",
      "round": "QF",
      "best_of": "3",
      "rank": "",
      "opp_rank": "",
      "result": "L",
      "opponent": "O. Krutykh",
      "score": "2-6 1-6"
    },
    {
      "date": "20200903",
      "tournament": "M15 Novomoskovsk",
      "surface": "Hard",
      "level": "I",
      "round": "R16",
      "best_of": "3",
      "rank": "",
      "opp_rank": "",
      "result": "W",
      "opponent": "Y. Dzhavakian",
      "score": "7-5 4-6 6(3)-7(7)"
    },
    {
      "date": "20200901",
      "tournament": "M15 Novomoskovsk",
      "surface": "Hard",
      "level": "I",
      "round": "R32",
      "best_of": "3",
      "rank": "",
      "opp_rank": "",
      "result": "W",
      "opponent": "D. Slyepkan",
      "score": "3-6 1-6"
    },
    {
      "date": "20200304",
      "tournament": "M25 Murcia",
      "surface": "Hard",
      "level": "I",
      "round": "R32",
      "best_of": "3",
      "rank": "",
      "opp_rank": "",
      "result": "L",
      "opponent": "T. Deschamps",
      "score": "6-3 7(7)-6(3)"
    },
    {
      "date": "20200123",
      "tournament": "M15 Kazan",
      "surface": "Hard",
      "level": "I",
      "round": "R16",
      "best_of": "3",
      "rank": "",
      "opp_rank": "",
      "result": "L",
      "opponent": "M. Ratniuk",
      "score": "6(2)-7(7) 4-6"
    },
    {
      "date": "20200122",
      "tournament": "M15 Kazan",
      "surface": "Hard",
      "level": "I",
      "round": "R32",
      "best_of": "3",
      "rank": "",
      "opp_rank": "",
      "result": "W",
      "opponent": "K. Lozan",
      "score": "6(4)-7(7) 2-6"
    },
    {
      "date": "20200116",
      "tournament": "ITF M15 Monastir 2 Men",
      "surface": "Hard",
      "level": "I",
      "round": "R16",
      "best_of": "3",
      "rank": "",
      "opp_rank": "",
      "result": "L",
      "opponent": "M. Kilani",
      "score": "6-2 7(7)-6(3)"
    },
    {
      "date": "20200115",
      "tournament": "ITF M15 Monastir 2 Men",
      "surface": "Hard",
      "level": "I",
      "round": "R32",
      "best_of": "3",
      "rank": "",
      "opp_rank": "",
      "result": "W",
      "opponent": "H. Schott",
      "score": "3-6 6-4 6-3"
    },
    {
      "date": "20200110",
      "tournament": "ITF M15 Monastir Men",
      "surface": "Hard",
      "level": "I",
      "round": "QF",
      "best_of": "3",
      "rank": "",
      "opp_rank": "",
      "result": "L",
      "opponent": "T. Laurent",
      "score": "7(7)-6(2) 6-1"
    },
    {
      "date": "20200109",
      "tournament": "ITF M15 Monastir Men",
      "surface": "Hard",
      "level": "I",
      "round": "R16",
      "best_of": "3",
      "rank": "",
      "opp_rank": "",
      "result": "W",
      "opponent": "U. Blanchet",
      "score": "6-2 6(5)-7(7) 6-4"
    },
    {
      "date": "20200108",
      "tournament": "ITF M15 Monastir Men",
      "surface": "Hard",
      "level": "I",
      "round": "R32",
      "best_of": "3",
      "rank": "",
      "opp_rank": "",
      "result": "W",
      "opponent": "P. Boerma",
      "score": "6-4 6-3"
    },
    {
      "date": "20191002",
      "tournament": "Nur-Sultan 2",
      "surface": "Hard",
      "level": "C",
      "round": "R32",
      "best_of": "3",
      "rank": "",
      "opp_rank": "",
      "result": "L",
      "opponent": "R. Bemelmans",
      "score": "6-4 6-3"
    },
    {
      "date": "20191001",
      "tournament": "Nur-Sultan 2",
      "surface": "Hard",
      "level": "C",
      "round": "R64",
      "best_of": "3",
      "rank": "",
      "opp_rank": "",
      "result": "W",
      "opponent": "J. Karimov",
      "score": "6-3 6-4"
    },
    {
      "date": "20190731",
      "tournament": "Sopot",
      "surface": "Hard",
      "level": "C",
      "round": "R32",
      "best_of": "3",
      "rank": "",
      "opp_rank": "",
      "result": "L",
      "opponent": "M. Ymer",
      "score": "2-6 3-6"
    },
    {
      "date": "20190729",
      "tournament": "Sopot",
      "surface": "Hard",
      "level": "C",
      "round": "R64",
      "best_of": "3",
      "rank": "",
      "opp_rank": "",
      "result": "W",
      "opponent": "J. Berrettini",
      "score": "6-3 7-5"
    },
    {
      "date": "20190718",
      "tournament": "Amersfoort",
      "surface": "Hard",
      "level": "C",
      "round": "R16",
      "best_of": "3",
      "rank": "",
      "opp_rank": "",
      "result": "L",
      "opponent": "Z. Kolar",
      "score": "6-1 7(7)-6(5)"
    },
    {
      "date": "20190717",
      "tournament": "Amersfoort",
      "surface": "Hard",
      "level": "C",
      "round": "R32",
      "best_of": "3",
      "rank": "",
      "opp_rank": "",
      "result": "W",
      "opponent": "N. Kuhn",
      "score": "5-7 6-4 3-6"
    },
    {
      "date": "20190716",
      "tournament": "Amersfoort",
      "surface": "Hard",
      "level": "C",
      "round": "R64",
      "best_of": "3",
      "rank": "",
      "opp_rank": "",
      "result": "W",
      "opponent": "S. Robert",
      "score": "7-5 5-7 2-6"
    },
    {
      "date": "20190420",
      "tournament": "Madrid",
      "surface": "Hard",
      "level": "I",
      "round": "QF",
      "best_of": "3",
      "rank": "",
      "opp_rank": "",
      "result": "W",
      "opponent": "P. T. Lipovsek",
      "score": "6-0 6-3"
    },
    {
      "date": "20190420",
      "tournament": "Madrid",
      "surface": "Hard",
      "level": "I",
      "round": "SF",
      "best_of": "3",
      "rank": "",
      "opp_rank": "",
      "result": "L",
      "opponent": "C. Denolly",
      "score": "7(7)-6(5) 6-4"
    },
    {
      "date": "20190419",
      "tournament": "Madrid",
      "surface": "Hard",
      "level": "I",
      "round": "R16",
      "best_of": "3",
      "rank": "",
      "opp_rank": "",
      "result": "W",
      "opponent": "J. Echeverria",
      "score": "6-2 6-2"
    },
    {
      "date": "20190417",
      "tournament": "Madrid",
      "surface": "Hard",
      "level": "I",
      "round": "R32",
      "best_of": "3",
      "rank": "",
      "opp_rank": "",
      "result": "W",
      "opponent": "D. Gennaro",
      "score": "6-3 6-1"
    },
    {
      "date": "20190408",
      "tournament": "Murcia",
      "surface": "Hard",
      "level": "C",
      "round": "R64",
      "best_of": "3",
      "rank": "",
      "opp_rank": "",
      "result": "L",
      "opponent": "B. Bonzi",
      "score": "3-6 6-3 3-6"
    },
    {
      "date": "20190120",
      "tournament": "M15 Manacor (Mallorca) 2",
      "surface": "Hard",
      "level": "I",
      "round": "F",
      "best_of": "3",
      "rank": "",
      "opp_rank": "",
      "result": "L",
      "opponent": "F. Cerundolo",
      "score": "6-3 6-3"
    },
    {
      "date": "20190119",
      "tournament": "M15 Manacor (Mallorca) 2",
      "surface": "Hard",
      "level": "I",
      "round": "SF",
      "best_of": "3",
      "rank": "",
      "opp_rank": "",
      "result": "W",
      "opponent": "M. Eriksson",
      "score": "6-3 6-3"
    },
    {
      "date": "20190118",
      "tournament": "M15 Manacor (Mallorca) 2",
      "surface": "Hard",
      "level": "I",
      "round": "QF",
      "best_of": "3",
      "rank": "",
      "opp_rank": "",
      "result": "W",
      "opponent": "J. Nikles",
      "score": "7-5 6-4"
    },
    {
      "date": "20190117",
      "tournament": "M15 Manacor (Mallorca) 2",
      "surface": "Hard",
      "level": "I",
      "round": "R16",
      "best_of": "3",
      "rank": "",
      "opp_rank": "",
      "result": "W",
      "opponent": "F. Diep",
      "score": "6-2 6-4"
    },
    {
      "date": "20190115",
      "tournament": "M15 Manacor (Mallorca) 2",
      "surface": "Hard",
      "level": "I",
      "round": "R32",
      "best_of": "3",
      "rank": "",
      "opp_rank": "",
      "result": "W",
      "opponent": "M. Mora",
      "score": "3-6 7-5 6-1"
    },
    {
      "date": "20190109",
      "tournament": "M15 Manacor (Mallorca)",
      "surface": "Hard",
      "level": "I",
      "round": "R32",
      "best_of": "3",
      "rank": "",
      "opp_rank": "",
      "result": "L",
      "opponent": "P. Vives Marcos",
      "score": "6-3 6-3"
    },
    {
      "date": "20180718",
      "tournament": "Nur-Sultan",
      "surface": "Hard",
      "level": "C",
      "round": "R16",
      "best_of": "3",
      "rank": "",
      "opp_rank": "",
      "result": "L",
      "opponent": "D. Brands",
      "score": "6(3)-7(7) 6-3 6-3"
    },
    {
      "date": "20180717",
      "tournament": "Nur-Sultan",
      "surface": "Hard",
      "level": "C",
      "round": "R32",
      "best_of": "3",
      "rank": "",
      "opp_rank": "",
      "result": "W",
      "opponent": "H. Ehara",
      "score": "3-6 6(5)-7(7)"
    },
    {
      "date": "20180403",
      "tournament": "Alicante",
      "surface": "Hard",
      "level": "C",
      "round": "R32",
      "best_of": "3",
      "rank": "",
      "opp_rank": "",
      "result": "L",
      "opponent": "A. Giannessi",
      "score": "6-1 7(7)-6(1)"
    },
    {
      "date": "20180315",
      "tournament": "Xabia",
      "surface": "Hard",
      "level": "I",
      "round": "R16",
      "best_of": "3",
      "rank": "",
      "opp_rank": "",
      "result": "L",
      "opponent": "M. Giner",
      "score": "3-6 1-6"
    },
    {
      "date": "20180314",
      "tournament": "Xabia",
      "surface": "Hard",
      "level": "I",
      "round": "R32",
      "best_of": "3",
      "rank": "",
      "opp_rank": "",
      "result": "W",
      "opponent": "R. Brancaccio",
      "score": "4-6 6-1 3-6"
    },
    {
      "date": "20180216",
      "tournament": "M25 Murcia",
      "surface": "Hard",
      "level": "I",
      "round": "QF",
      "best_of": "3",
      "rank": "",
      "opp_rank": "",
      "result": "L",
      "opponent": "D. Gimeno-Traver",
      "score": "6-3 6(6)-7(8) 3-6"
    },
    {
      "date": "20180215",
      "tournament": "M25 Murcia",
      "surface": "Hard",
      "level": "I",
      "round": "R16",
      "best_of": "3",
      "rank": "",
      "opp_rank": "",
      "result": "W",
      "opponent": "M. Semmler",
      "score": "6-1 2-6 3-6"
    },
    {
      "date": "20180214",
      "tournament": "M25 Murcia",
      "surface": "Hard",
      "level": "I",
      "round": "R32",
      "best_of": "3",
      "rank": "",
      "opp_rank": "",
      "result": "W",
      "opponent": "C. S. Perez",
      "score": "5-7 3-6"
    },
    {
      "date": "20180128",
      "tournament": "M15 Manacor (Mallorca) 2",
      "surface": "Hard",
      "level": "I",
      "round": "SF",
      "best_of": "3",
      "rank": "",
      "opp_rank": "",
      "result": "L",
      "opponent": "L. Giustino",
      "score": "6-1 6-2"
    },
    {
      "date": "20180126",
      "tournament": "M15 Manacor (Mallorca) 2",
      "surface": "Hard",
      "level": "I",
      "round": "QF",
      "best_of": "3",
      "rank": "",
      "opp_rank": "",
      "result": "W",
      "opponent": "A. Musialek",
      "score": "6-3 2-6 2-6"
    },
    {
      "date": "20180124",
      "tournament": "M15 Manacor (Mallorca) 2",
      "surface": "Hard",
      "level": "I",
      "round": "R16",
      "best_of": "3",
      "rank": "",
      "opp_rank": "",
      "result": "W",
      "opponent": "G. Gigounon",
      "score": "1-6 3-6"
    },
    {
      "date": "20180122",
      "tournament": "M15 Manacor (Mallorca) 2",
      "surface": "Hard",
      "level": "I",
      "round": "R32",
      "best_of": "3",
      "rank": "",
      "opp_rank": "",
      "result": "W",
      "opponent": "A. Kalyanpur",
      "score": "7-5 1-6 2-6"
    },
    {
      "date": "20170217",
      "tournament": "M25 Murcia",
      "surface": "Hard",
      "level": "I",
      "round": "QF",
      "best_of": "3",
      "rank": "",
      "opp_rank": "",
      "result": "L",
      "opponent": "D. Munoz-De La Nava",
      "score": "7-5 4-6 6-1"
    },
    {
      "date": "20170216",
      "tournament": "M25 Murcia",
      "surface": "Hard",
      "level": "I",
      "round": "R16",
      "best_of": "3",
      "rank": "",
      "opp_rank": "",
      "result": "W",
      "opponent": "P. Cachin",
      "score": "3-6 7-6 6-3"
    },
    {
      "date": "20170215",
      "tournament": "M25 Murcia",
      "surface": "Hard",
      "level": "I",
      "round": "R32",
      "best_of": "3",
      "rank": "",
      "opp_rank": "",
      "result": "W",
      "opponent": "S. Gutierrez-Ferrol",
      "score": "6-3 6-4"
    },
    {
      "date": "20150218",
      "tournament": "M25 Murcia",
      "surface": "Hard",
      "level": "I",
      "round": "R32",
      "best_of": "3",
      "rank": "",
      "opp_rank": "",
      "result": "L",
      "opponent": "O. Roca Batalla",
      "score": "6-3 6-2"
    },
    {
      "date": "20140425",
      "tournament": "Madrid",
      "surface": "Hard",
      "level": "I",
      "round": "QF",
      "best_of": "3",
      "rank": "",
      "opp_rank": "",
      "result": "L",
      "opponent": "M. Giner",
      "score": "7(7)-6(5) 6-2"
    },
    {
      "date": "20140424",
      "tournament": "Madrid",
      "surface": "Hard",
      "level": "I",
      "round": "R16",
      "best_of": "3",
      "rank": "",
      "opp_rank": "",
      "result": "W",
      "opponent": "J. Blecha",
      "score": "6-3 6(4)-7(7) 2-6"
    },
    {
      "date": "20140423",
      "tournament": "Madrid",
      "surface": "Hard",
      "level": "I",
      "round": "R32",
      "best_of": "3",
      "rank": "",
      "opp_rank": "",
      "result": "W",
      "opponent": "I. Gomez Mantilla",
      "score": "6-3 7(9)-6(7)"
    }
  ]
}