{
  "player_id": "ki82",
  "player_name": "Vit Kopriva",
  "source": "sackmann+goalserve",
  "updated": "2026-03-25T21:23:11.523Z",
  "matches": [
    {
      "date": "20260303",
      "tournament": "Indian Wells",
      "surface": "Hard",
      "level": "B",
      "round": "SF",
      "best_of": "3",
      "result": "W",
      "opponent": "R. Sakamoto",
      "score": "6-4 7(8)-6(6)"
    },
    {
      "date": "20260218",
      "tournament": "Rio de Janeiro",
      "surface": "Hard",
      "level": "B",
      "round": "R16",
      "best_of": "3",
      "result": "W",
      "opponent": "R. A. Burruchaga",
      "score": "3-6 1-6"
    },
    {
      "date": "20260216",
      "tournament": "Rio de Janeiro",
      "surface": "Hard",
      "level": "B",
      "round": "R32",
      "best_of": "3",
      "result": "W",
      "opponent": "G. Heide",
      "score": "2-6 6(5)-7(7)"
    },
    {
      "date": "20260209",
      "tournament": "Buenos Aires",
      "surface": "Hard",
      "level": "B",
      "round": "R32",
      "best_of": "3",
      "result": "W",
      "opponent": "A. Barrena",
      "score": "4-6 6-3 4-6"
    },
    {
      "date": "20260110",
      "tournament": "Auckland",
      "surface": "Hard",
      "level": "B",
      "round": "F",
      "best_of": "3",
      "result": "L",
      "opponent": "H. Gaston",
      "score": "6-2 6-4"
    },
    {
      "date": "20260109",
      "tournament": "Auckland",
      "surface": "Hard",
      "level": "B",
      "round": "SF",
      "best_of": "3",
      "result": "W",
      "opponent": "P. Carreno-Busta",
      "score": "6-3 1-6 6-4"
    },
    {
      "date": "20251025",
      "tournament": "Paris",
      "surface": "Hard",
      "level": "B",
      "round": "SF",
      "best_of": "3",
      "result": "L",
      "opponent": "S. Korda",
      "score": "2-6 5-7"
    },
    {
      "date": "20251018",
      "tournament": "Vienna",
      "surface": "Hard",
      "level": "B",
      "round": "SF",
      "best_of": "3",
      "result": "L",
      "opponent": "E. Quinn",
      "score": "4-6 6-1 6-1"
    },
    {
      "date": "20250818",
      "tournament": "Winston-Salem",
      "surface": "Hard",
      "level": "B",
      "round": "R32",
      "best_of": "3",
      "result": "L",
      "opponent": "S. Korda",
      "score": "6-3 6-4"
    },
    {
      "date": "20250817",
      "tournament": "Winston-Salem",
      "surface": "Hard",
      "level": "B",
      "round": "R64",
      "best_of": "3",
      "result": "W",
      "opponent": "S. Ofner",
      "score": "6-3 4-6 3-6"
    },
    {
      "date": "20250728",
      "tournament": "Toronto",
      "surface": "Hard",
      "level": "B",
      "round": "R128",
      "best_of": "3",
      "result": "L",
      "opponent": "Y. Bu",
      "score": "7(7)-6(4) 6-2"
    },
    {
      "date": "20250723",
      "tournament": "Umag",
      "surface": "Hard",
      "level": "B",
      "round": "R16",
      "best_of": "3",
      "result": "L",
      "opponent": "T. Droguet",
      "score": "2-6 3-6"
    },
    {
      "date": "20250720",
      "tournament": "Umag",
      "surface": "Hard",
      "level": "B",
      "round": "R32",
      "best_of": "3",
      "result": "W",
      "opponent": "R. Collignon",
      "score": "6-3 4-6 3-6"
    },
    {
      "date": "20250505",
      "tournament": "Rome",
      "surface": "Hard",
      "level": "B",
      "round": "SF",
      "best_of": "3",
      "result": "W",
      "opponent": "D. Svrcina",
      "score": "6-2 5-7 6-2"
    },
    {
      "date": "20250113",
      "tournament": "Nonthaburi 3",
      "surface": "Hard",
      "level": "C",
      "round": "R32",
      "best_of": "3",
      "result": "W",
      "opponent": "N. Hardt",
      "score": "6-4 6-1"
    },
    {
      "date": "20250102",
      "tournament": "Canberra",
      "surface": "Hard",
      "level": "C",
      "round": "QF",
      "best_of": "3",
      "result": "L",
      "opponent": "E. Quinn",
      "score": "6-4 7-5"
    },
    {
      "date": "20250101",
      "tournament": "Canberra",
      "surface": "Hard",
      "level": "C",
      "round": "R16",
      "best_of": "3",
      "result": "W",
      "opponent": "D. Dzumhur",
      "score": "5-7 5-7"
    },
    {
      "date": "20241230",
      "tournament": "Canberra",
      "surface": "Hard",
      "level": "C",
      "round": "R32",
      "best_of": "3",
      "result": "W",
      "opponent": "M. Krueger",
      "score": "7(7)-6(5) 3-6 6-3"
    },
    {
      "date": "20241110",
      "tournament": "Lima 2",
      "surface": "Hard",
      "level": "C",
      "round": "F",
      "best_of": "3",
      "result": "W",
      "opponent": "E. Moller",
      "score": "6-3 7(7)-6(3)"
    },
    {
      "date": "20241109",
      "tournament": "Lima 2",
      "surface": "Hard",
      "level": "C",
      "round": "QF",
      "best_of": "3",
      "result": "W",
      "opponent": "F. Comesana",
      "score": "6-4 6(3)-7(7) 1-6"
    },
    {
      "date": "20241109",
      "tournament": "Lima 2",
      "surface": "Hard",
      "level": "C",
      "round": "SF",
      "best_of": "3",
      "result": "W",
      "opponent": "J. M. Cerundolo",
      "score": "3-6 6-4 6-2"
    },
    {
      "date": "20241107",
      "tournament": "Lima 2",
      "surface": "Hard",
      "level": "C",
      "round": "R16",
      "best_of": "3",
      "result": "W",
      "opponent": "M. Trungelliti",
      "score": "3-6 6-4 6-3"
    },
    {
      "date": "20241106",
      "tournament": "Lima 2",
      "surface": "Hard",
      "level": "C",
      "round": "R32",
      "best_of": "3",
      "result": "W",
      "opponent": "G. Bueno",
      "score": "6-4 4-6 6-3"
    },
    {
      "date": "20241008",
      "tournament": "Valencia",
      "surface": "Hard",
      "level": "C",
      "round": "R32",
      "best_of": "3",
      "result": "L",
      "opponent": "J. J. Schwaerzler",
      "score": "5-7 4-6"
    },
    {
      "date": "20240910",
      "tournament": "Szczecin",
      "surface": "Hard",
      "level": "C",
      "round": "R32",
      "best_of": "3",
      "result": "W",
      "opponent": "N. Moreno De Alboran",
      "score": "2-6 7-5 6-1"
    },
    {
      "date": "20240903",
      "tournament": "Tulln Challenger Men",
      "surface": "Hard",
      "level": "C",
      "round": "R32",
      "best_of": "3",
      "result": "L",
      "opponent": "J. Choinski",
      "score": "1-6 6-3 6-4"
    },
    {
      "date": "20240820",
      "tournament": "ATP US Open",
      "surface": "Hard",
      "level": "G",
      "round": "QF",
      "best_of": "3",
      "result": "L",
      "opponent": "M. Krueger",
      "score": "3-6 3-6"
    },
    {
      "date": "20240814",
      "tournament": "Grodzisk Mazowiecki Challenger Men",
      "surface": "Hard",
      "level": "C",
      "round": "R16",
      "best_of": "3",
      "result": "W",
      "opponent": "F. Peliwo",
      "score": "6-3 7-5"
    },
    {
      "date": "20240813",
      "tournament": "Grodzisk Mazowiecki Challenger Men",
      "surface": "Hard",
      "level": "C",
      "round": "R32",
      "best_of": "3",
      "result": "W",
      "opponent": "M. Pawelski",
      "score": "6-4 6-3"
    },
    {
      "date": "20240721",
      "tournament": "ATP Kitzbuhel",
      "surface": "Hard",
      "level": "B",
      "round": "F",
      "best_of": "3",
      "result": "W",
      "opponent": "G. Heide",
      "score": "3-6 6-3 7-5"
    },
    {
      "date": "20240720",
      "tournament": "ATP Kitzbuhel",
      "surface": "Hard",
      "level": "B",
      "round": "SF",
      "best_of": "3",
      "result": "W",
      "opponent": "I. Buse",
      "score": "6-1 6(3)-7(7) 6-1"
    },
    {
      "date": "20240715",
      "tournament": "ATP Gstaad",
      "surface": "Hard",
      "level": "B",
      "round": "R32",
      "best_of": "3",
      "result": "L",
      "opponent": "D. E. Galan",
      "score": "6-3 6-2"
    },
    {
      "date": "20240709",
      "tournament": "Salzburg",
      "surface": "Hard",
      "level": "C",
      "round": "R32",
      "best_of": "3",
      "result": "W",
      "opponent": "T. Kodat",
      "score": "6-4 7(7)-6(3)"
    },
    {
      "date": "20240624",
      "tournament": "ATP Wimbledon",
      "surface": "Hard",
      "level": "G",
      "round": "QF",
      "best_of": "3",
      "result": "W",
      "opponent": "H. Squire",
      "score": "4-6 7(7)-6(1) 6-4"
    },
    {
      "date": "20240605",
      "tournament": "Prostejov Challenger Men",
      "surface": "Hard",
      "level": "C",
      "round": "R16",
      "best_of": "3",
      "result": "L",
      "opponent": "C. H. Tseng",
      "score": "6-4 6-2"
    },
    {
      "date": "20240604",
      "tournament": "Prostejov Challenger Men",
      "surface": "Hard",
      "level": "C",
      "round": "R32",
      "best_of": "3",
      "result": "W",
      "opponent": "S. Travaglia",
      "score": "6-4 6-4"
    },
    {
      "date": "20240522",
      "tournament": "ATP French Open",
      "surface": "Hard",
      "level": "G",
      "round": "SF",
      "best_of": "3",
      "result": "L",
      "opponent": "D. Kudla",
      "score": "6-3 3-6 3-6"
    },
    {
      "date": "20240520",
      "tournament": "ATP French Open",
      "surface": "Hard",
      "level": "G",
      "round": "QF",
      "best_of": "3",
      "result": "W",
      "opponent": "M. Valkusz",
      "score": "3-6 2-6"
    },
    {
      "date": "20240507",
      "tournament": "ATP Rome",
      "surface": "Hard",
      "level": "B",
      "round": "F",
      "best_of": "3",
      "result": "L",
      "opponent": "N. Moreno De Alboran",
      "score": "6-4 3-6 6-3"
    },
    {
      "date": "20240506",
      "tournament": "ATP Rome",
      "surface": "Hard",
      "level": "B",
      "round": "SF",
      "best_of": "3",
      "result": "W",
      "opponent": "F. Coria",
      "score": "3-6 7-5 6(3)-7(7)"
    },
    {
      "date": "20240422",
      "tournament": "ATP Madrid",
      "surface": "Hard",
      "level": "B",
      "round": "SF",
      "best_of": "3",
      "result": "L",
      "opponent": "A. Shelbayh",
      "score": "1-6 6-1 1-6"
    },
    {
      "date": "20240415",
      "tournament": "ATP Munich",
      "surface": "Hard",
      "level": "B",
      "round": "R32",
      "best_of": "3",
      "result": "L",
      "opponent": "J. Draper",
      "score": "6-1 5-7 6-4"
    },
    {
      "date": "20240318",
      "tournament": "ATP Miami",
      "surface": "Hard",
      "level": "B",
      "round": "SF",
      "best_of": "3",
      "result": "W",
      "opponent": "R. Sakamoto",
      "score": "6(5)-7(7) 6(5)-7(7)"
    },
    {
      "date": "20240306",
      "tournament": "ATP Indian Wells",
      "surface": "Hard",
      "level": "B",
      "round": "F",
      "best_of": "3",
      "result": "L",
      "opponent": "C. Lestienne",
      "score": "1-6 3-6"
    },
    {
      "date": "20240304",
      "tournament": "ATP Indian Wells",
      "surface": "Hard",
      "level": "B",
      "round": "SF",
      "best_of": "3",
      "result": "W",
      "opponent": "C. Woestendick",
      "score": "2-6 3-6"
    },
    {
      "date": "20240219",
      "tournament": "ATP Doha",
      "surface": "Hard",
      "level": "B",
      "round": "R32",
      "best_of": "3",
      "result": "L",
      "opponent": "F. Marozsan",
      "score": "5-7 6(6)-7(8)"
    },
    {
      "date": "20240218",
      "tournament": "ATP Doha",
      "surface": "Hard",
      "level": "B",
      "round": "F",
      "best_of": "3",
      "result": "W",
      "opponent": "M. Marterer",
      "score": "3-6 1-6"
    },
    {
      "date": "20240217",
      "tournament": "ATP Doha",
      "surface": "Hard",
      "level": "B",
      "round": "SF",
      "best_of": "3",
      "result": "W",
      "opponent": "M. S. Zayid",
      "score": "2-6 4-6"
    },
    {
      "date": "20240125",
      "tournament": "Quimper Challenger Men",
      "surface": "Hard",
      "level": "C",
      "round": "R16",
      "best_of": "3",
      "result": "L",
      "opponent": "M. Martineau",
      "score": "7-5 6-4"
    },
    {
      "date": "20240124",
      "tournament": "Quimper Challenger Men",
      "surface": "Hard",
      "level": "C",
      "round": "R32",
      "best_of": "3",
      "result": "W",
      "opponent": "L. Pouille",
      "score": "6-2 6-4"
    },
    {
      "date": "20240109",
      "tournament": "ATP Australian Open",
      "surface": "Hard",
      "level": "G",
      "round": "QF",
      "best_of": "3",
      "result": "W",
      "opponent": "C. Hemery",
      "score": "3-6 3-6"
    },
    {
      "date": "20230904",
      "tournament": "Tulln Challenger Men",
      "surface": "Hard",
      "level": "C",
      "round": "R32",
      "best_of": "3",
      "result": "W",
      "opponent": "Z. Kolar",
      "score": "6-2 7(7)-6(4)"
    },
    {
      "date": "20230823",
      "tournament": "ATP US Open",
      "surface": "Hard",
      "level": "G",
      "round": "QF",
      "best_of": "3",
      "result": "L",
      "opponent": "M. Cressy",
      "score": "3-6 3-6"
    },
    {
      "date": "20230719",
      "tournament": "Tampere Challenger Men",
      "surface": "Hard",
      "level": "C",
      "round": "R16",
      "best_of": "3",
      "result": "L",
      "opponent": "L. Klein",
      "score": "5-7 1-6"
    },
    {
      "date": "20230717",
      "tournament": "Tampere Challenger Men",
      "surface": "Hard",
      "level": "C",
      "round": "R32",
      "best_of": "3",
      "result": "W",
      "opponent": "G. Fonio",
      "score": "4-6 6(6)-7(8)"
    },
    {
      "date": "20230713",
      "tournament": "Salzburg Challenger Men",
      "surface": "Hard",
      "level": "C",
      "round": "R16",
      "best_of": "3",
      "result": "L",
      "opponent": "B. Rola",
      "score": "3-6 6-1 3-6"
    },
    {
      "date": "20230711",
      "tournament": "Salzburg Challenger Men",
      "surface": "Hard",
      "level": "C",
      "round": "R32",
      "best_of": "3",
      "result": "W",
      "opponent": "N. Oberleitner",
      "score": "7(8)-6(6) 1-6 1-6"
    },
    {
      "date": "20230703",
      "tournament": "Karlsruhe Challenger Men",
      "surface": "Hard",
      "level": "C",
      "round": "R32",
      "best_of": "3",
      "result": "L",
      "opponent": "L. Riedi",
      "score": "4-6 6-3 6-2"
    },
    {
      "date": "20230626",
      "tournament": "ATP Wimbledon",
      "surface": "Hard",
      "level": "G",
      "round": "QF",
      "best_of": "3",
      "result": "L",
      "opponent": "L. Klein",
      "score": "3-6 4-6"
    },
    {
      "date": "20230530",
      "tournament": "Vicenza Challenger Men",
      "surface": "Hard",
      "level": "C",
      "round": "R32",
      "best_of": "3",
      "result": "L",
      "opponent": "A. Collarini",
      "score": "6-0 7-5"
    },
    {
      "date": "20230522",
      "tournament": "ATP French Open",
      "surface": "Hard",
      "level": "G",
      "round": "QF",
      "best_of": "3",
      "result": "L",
      "opponent": "R. Albot",
      "score": "5-7 0-6"
    },
    {
      "date": "20230425",
      "tournament": "Ostrava Challenger Men",
      "surface": "Hard",
      "level": "C",
      "round": "R32",
      "best_of": "3",
      "result": "W",
      "opponent": "D. Added",
      "score": "7-5 4-6 6-3"
    },
    {
      "date": "20230416",
      "tournament": "ATP Munich",
      "surface": "Hard",
      "level": "B",
      "round": "F",
      "best_of": "3",
      "result": "L",
      "opponent": "M. Topo",
      "score": "6-4 4-6 6-3"
    },
    {
      "date": "20230415",
      "tournament": "ATP Munich",
      "surface": "Hard",
      "level": "B",
      "round": "SF",
      "best_of": "3",
      "result": "W",
      "opponent": "A. Lopez San Martin",
      "score": "6(3)-7(7) 6-3 7(7)-6(3)"
    },
    {
      "date": "20230408",
      "tournament": "ATP Monte Carlo",
      "surface": "Hard",
      "level": "B",
      "round": "SF",
      "best_of": "3",
      "result": "L",
      "opponent": "A. Popyrin",
      "score": "3-6 6-3 6-1"
    },
    {
      "date": "20230402",
      "tournament": "ATP Marrakech",
      "surface": "Hard",
      "level": "B",
      "round": "SF",
      "best_of": "3",
      "result": "L",
      "opponent": "R. Bennani",
      "score": "7(7)-6(4) 7-5"
    },
    {
      "date": "20230327",
      "tournament": "Sanremo",
      "surface": "Hard",
      "level": "C",
      "round": "R32",
      "best_of": "3",
      "result": "W",
      "opponent": "M. Cecchinato",
      "score": "6-4 6-4"
    },
    {
      "date": "20230321",
      "tournament": "Zadar Challenger Men",
      "surface": "Hard",
      "level": "C",
      "round": "R32",
      "best_of": "3",
      "result": "L",
      "opponent": "H. Medjedovic",
      "score": "4-6 2-6"
    },
    {
      "date": "20230218",
      "tournament": "Doha",
      "surface": "Hard",
      "level": "B",
      "round": "SF",
      "best_of": "3",
      "result": "L",
      "opponent": "T. Machac",
      "score": "7(7)-6(2) 7(9)-6(7)"
    },
    {
      "date": "20221115",
      "tournament": "Helsinki",
      "surface": "Hard",
      "level": "C",
      "round": "R32",
      "best_of": "3",
      "result": "L",
      "opponent": "J. Sels",
      "score": "6-3 6(5)-7(7) 6-3"
    },
    {
      "date": "20221108",
      "tournament": "Bratislava 2",
      "surface": "Hard",
      "level": "C",
      "round": "R32",
      "best_of": "3",
      "result": "L",
      "opponent": "J. Kovalik",
      "score": "6(5)-7(7) 6(3)-7(7)"
    },
    {
      "date": "20221031",
      "tournament": "Bergamo",
      "surface": "Hard",
      "level": "C",
      "round": "R32",
      "best_of": "3",
      "result": "W",
      "opponent": "D. Kuzmanov",
      "score": "6-4 2-6 1-6"
    },
    {
      "date": "20221015",
      "tournament": "Stockholm",
      "surface": "Hard",
      "level": "B",
      "round": "SF",
      "best_of": "3",
      "result": "L",
      "opponent": "N. D. Ionel",
      "score": "6(4)-7(7) 5-7"
    },
    {
      "date": "20221006",
      "tournament": "Parma 2",
      "surface": "Hard",
      "level": "C",
      "round": "R16",
      "best_of": "3",
      "result": "W",
      "opponent": "Z. Kolar",
      "score": "6-3 2-6 6-3"
    },
    {
      "date": "20221004",
      "tournament": "Parma 2",
      "surface": "Hard",
      "level": "C",
      "round": "R32",
      "best_of": "3",
      "result": "W",
      "opponent": "O. Roca Batalla",
      "score": "7(9)-6(7) 6-1"
    },
    {
      "date": "20220919",
      "tournament": "Braga",
      "surface": "Hard",
      "level": "C",
      "round": "R32",
      "best_of": "3",
      "result": "L",
      "opponent": "J. Domingues",
      "score": "7-5 4-6 2-6"
    },
    {
      "date": "20220725",
      "tournament": "Kitzbuhel",
      "surface": "Hard",
      "level": "B",
      "round": "R32",
      "best_of": "3",
      "result": "L",
      "opponent": "J. Sousa",
      "score": "6-1 7-5"
    },
    {
      "date": "20220724",
      "tournament": "Kitzbuhel",
      "surface": "Hard",
      "level": "B",
      "round": "F",
      "best_of": "3",
      "result": "W",
      "opponent": "A. Shevchenko",
      "score": "1-6 6-4 6-4"
    },
    {
      "date": "20220723",
      "tournament": "Kitzbuhel",
      "surface": "Hard",
      "level": "B",
      "round": "SF",
      "best_of": "3",
      "result": "W",
      "opponent": "L. Neumayer",
      "score": "3-6 6-4 6-1"
    },
    {
      "date": "20220718",
      "tournament": "Gstaad",
      "surface": "Hard",
      "level": "B",
      "round": "F",
      "best_of": "3",
      "result": "L",
      "opponent": "N. Jarry",
      "score": "4-6 4-6"
    },
    {
      "date": "20220717",
      "tournament": "Gstaad",
      "surface": "Hard",
      "level": "B",
      "round": "SF",
      "best_of": "3",
      "result": "W",
      "opponent": "P. Ender",
      "score": "1-6 2-6"
    },
    {
      "date": "20220705",
      "tournament": "Braunschweig",
      "surface": "Hard",
      "level": "C",
      "round": "R32",
      "best_of": "3",
      "result": "L",
      "opponent": "B. Zapata Miralles",
      "score": "1-6 1-6"
    },
    {
      "date": "20220618",
      "tournament": "Blois",
      "surface": "Hard",
      "level": "C",
      "round": "SF",
      "best_of": "3",
      "result": "L",
      "opponent": "N. Milojevic",
      "score": "6(1)-7(7) 2-6"
    },
    {
      "date": "20220617",
      "tournament": "Blois",
      "surface": "Hard",
      "level": "C",
      "round": "QF",
      "best_of": "3",
      "result": "W",
      "opponent": "M. Marterer",
      "score": "5-7 3-6"
    },
    {
      "date": "20220615",
      "tournament": "Blois",
      "surface": "Hard",
      "level": "C",
      "round": "R16",
      "best_of": "3",
      "result": "W",
      "opponent": "E. Nava",
      "score": "1-6 4-6"
    },
    {
      "date": "20220613",
      "tournament": "Blois",
      "surface": "Hard",
      "level": "C",
      "round": "R32",
      "best_of": "3",
      "result": "W",
      "opponent": "L. Giustino",
      "score": "6-2 4-6 6(5)-7(7)"
    },
    {
      "date": "20220405",
      "tournament": "Marrakech",
      "surface": "Hard",
      "level": "B",
      "round": "F",
      "best_of": "3",
      "result": "W",
      "opponent": "B. Zapata Miralles",
      "score": "6-0 1-6 5-7"
    },
    {
      "date": "20220403",
      "tournament": "Marrakech",
      "surface": "Hard",
      "level": "B",
      "round": "SF",
      "best_of": "3",
      "result": "W",
      "opponent": "M. Viola",
      "score": "4-6 3-6"
    },
    {
      "date": "20220311",
      "tournament": "Santiago",
      "surface": "Hard",
      "level": "C",
      "round": "QF",
      "best_of": "3",
      "result": "L",
      "opponent": "A. Tabilo",
      "score": "6-2 4-6 6-3"
    },
    {
      "date": "20220310",
      "tournament": "Santiago",
      "surface": "Hard",
      "level": "C",
      "round": "R16",
      "best_of": "3",
      "result": "W",
      "opponent": "N. Kicker",
      "score": "6-4 4-6 7-5"
    },
    {
      "date": "20220308",
      "tournament": "Santiago",
      "surface": "Hard",
      "level": "C",
      "round": "R32",
      "best_of": "3",
      "result": "W",
      "opponent": "N. Jarry",
      "score": "6-1 6(3)-7(7) 3-6"
    },
    {
      "date": "20220207",
      "tournament": "Bengaluru",
      "surface": "Hard",
      "level": "C",
      "round": "R32",
      "best_of": "3",
      "result": "L",
      "opponent": "H. Grenier",
      "score": "1-6 6-2 4-6"
    },
    {
      "date": "20220203",
      "tournament": "Pune",
      "surface": "Hard",
      "level": "B",
      "round": "R16",
      "best_of": "3",
      "result": "L",
      "opponent": "E. Ruusuvuori",
      "score": "3-6 3-6"
    },
    {
      "date": "20220201",
      "tournament": "Pune",
      "surface": "Hard",
      "level": "B",
      "round": "R32",
      "best_of": "3",
      "result": "W",
      "opponent": "C. Ilkel",
      "score": "6-4 6-2"
    },
    {
      "date": "20220131",
      "tournament": "Pune",
      "surface": "Hard",
      "level": "B",
      "round": "F",
      "best_of": "3",
      "result": "W",
      "opponent": "A. Celikbilek",
      "score": "7(7)-6(4) 3-6 5-7"
    },
    {
      "date": "20220130",
      "tournament": "Pune",
      "surface": "Hard",
      "level": "B",
      "round": "SF",
      "best_of": "3",
      "result": "W",
      "opponent": "M. Sureshkumar",
      "score": "2-6 3-6"
    },
    {
      "date": "20220112",
      "tournament": "Australian Open",
      "surface": "Hard",
      "level": "G",
      "round": "SF",
      "best_of": "3",
      "result": "L",
      "opponent": "E. Couacaud",
      "score": "6-3 6-3"
    },
    {
      "date": "20220107",
      "tournament": "Bendigo",
      "surface": "Hard",
      "level": "C",
      "round": "QF",
      "best_of": "3",
      "result": "L",
      "opponent": "E. Escobedo",
      "score": "3-6 7(7)-6(2) 6(2)-7(7)"
    },
    {
      "date": "20220106",
      "tournament": "Bendigo",
      "surface": "Hard",
      "level": "C",
      "round": "R16",
      "best_of": "3",
      "result": "W",
      "opponent": "F. Mena",
      "score": "6(11)-7(13) 6-4 3-6"
    },
    {
      "date": "20220104",
      "tournament": "Bendigo",
      "surface": "Hard",
      "level": "C",
      "round": "R32",
      "best_of": "3",
      "result": "W",
      "opponent": "C. Ilkel",
      "score": "7(7)-6(4) 6-3"
    },
    {
      "date": "20220103",
      "tournament": "Bendigo",
      "surface": "Hard",
      "level": "C",
      "round": "R64",
      "best_of": "3",
      "result": "W",
      "opponent": "R. Bemelmans",
      "score": "4-6 4-6"
    },
    {
      "date": "20211030",
      "tournament": "Lima 2 Challenger Men",
      "surface": "Hard",
      "level": "C",
      "round": "SF",
      "best_of": "3",
      "result": "L",
      "opponent": "N. Jarry",
      "score": "6-3 6-3"
    },
    {
      "date": "20211029",
      "tournament": "Lima 2 Challenger Men",
      "surface": "Hard",
      "level": "C",
      "round": "QF",
      "best_of": "3",
      "result": "W",
      "opponent": "T. Barrios",
      "score": "4-6 6-1 0-6"
    },
    {
      "date": "20211027",
      "tournament": "Lima 2 Challenger Men",
      "surface": "Hard",
      "level": "C",
      "round": "R16",
      "best_of": "3",
      "result": "W",
      "opponent": "T. Seyboth Wild",
      "score": "6-4 6-3"
    },
    {
      "date": "20211025",
      "tournament": "Lima 2 Challenger Men",
      "surface": "Hard",
      "level": "C",
      "round": "R32",
      "best_of": "3",
      "result": "W",
      "opponent": "R. Olivo",
      "score": "6-1 4-6 6-3"
    },
    {
      "date": "20211018",
      "tournament": "Bogota Challenger Men",
      "surface": "Hard",
      "level": "C",
      "round": "R32",
      "best_of": "3",
      "result": "L",
      "opponent": "A. Gonzalez",
      "score": "2-6 6(5)-7(7)"
    },
    {
      "date": "20210824",
      "tournament": "ATP US Open",
      "surface": "Hard",
      "level": "G",
      "round": "QF",
      "best_of": "3",
      "result": "L",
      "opponent": "H. Gaston",
      "score": "4-6 2-6"
    },
    {
      "date": "20210812",
      "tournament": "Meerbusch Challenger Men",
      "surface": "Hard",
      "level": "C",
      "round": "R16",
      "best_of": "3",
      "result": "L",
      "opponent": "D. Altmaier",
      "score": "6(3)-7(7) 6-3 3-6"
    },
    {
      "date": "20210810",
      "tournament": "Meerbusch Challenger Men",
      "surface": "Hard",
      "level": "C",
      "round": "R32",
      "best_of": "3",
      "result": "W",
      "opponent": "N. Fatic",
      "score": "7-5 6-2"
    },
    {
      "date": "20210727",
      "tournament": "Poznan Challenger Men",
      "surface": "Hard",
      "level": "C",
      "round": "R32",
      "best_of": "3",
      "result": "L",
      "opponent": "D. Popko",
      "score": "6-4 4-6 7-5"
    },
    {
      "date": "20210719",
      "tournament": "ATP Gstaad",
      "surface": "Hard",
      "level": "B",
      "round": "R32",
      "best_of": "3",
      "result": "W",
      "opponent": "J. Nikles",
      "score": "2-6 1-6"
    },
    {
      "date": "20210718",
      "tournament": "ATP Gstaad",
      "surface": "Hard",
      "level": "B",
      "round": "F",
      "best_of": "3",
      "result": "W",
      "opponent": "E. Couacaud",
      "score": "6-2 6(5)-7(7) 4-6"
    },
    {
      "date": "20210717",
      "tournament": "ATP Gstaad",
      "surface": "Hard",
      "level": "B",
      "round": "SF",
      "best_of": "3",
      "result": "W",
      "opponent": "M. Marterer",
      "score": "6-2 6-3"
    },
    {
      "date": "20210713",
      "tournament": "Amersfoort Challenger Men",
      "surface": "Hard",
      "level": "C",
      "round": "R32",
      "best_of": "3",
      "result": "L",
      "opponent": "L. Rosol",
      "score": "7(7)-6(4) 6-2"
    },
    {
      "date": "20210608",
      "tournament": "Bratislava Challenger Men",
      "surface": "Hard",
      "level": "C",
      "round": "R32",
      "best_of": "3",
      "result": "L",
      "opponent": "J. Kovalik",
      "score": "4-6 2-6"
    },
    {
      "date": "20210607",
      "tournament": "Bratislava Challenger Men",
      "surface": "Hard",
      "level": "C",
      "round": "F",
      "best_of": "3",
      "result": "W",
      "opponent": "O. Luz",
      "score": "6-2 6-4"
    },
    {
      "date": "20210606",
      "tournament": "Bratislava Challenger Men",
      "surface": "Hard",
      "level": "C",
      "round": "SF",
      "best_of": "3",
      "result": "W",
      "opponent": "L. Palovic",
      "score": "3-6 6-4 6-1"
    },
    {
      "date": "20210523",
      "tournament": "Belgrade 2",
      "surface": "Hard",
      "level": "B",
      "round": "F",
      "best_of": "3",
      "result": "L",
      "opponent": "R. Carballes Baena",
      "score": "4-6 4-6"
    },
    {
      "date": "20210522",
      "tournament": "Belgrade 2",
      "surface": "Hard",
      "level": "B",
      "round": "SF",
      "best_of": "3",
      "result": "W",
      "opponent": "A. Vatutin",
      "score": "3-6 6-3 4-6"
    },
    {
      "date": "20210503",
      "tournament": "Prague Challenger Men",
      "surface": "Hard",
      "level": "C",
      "round": "F",
      "best_of": "3",
      "result": "W",
      "opponent": "J. Rodionov",
      "score": "1-6 6-1 3-6"
    },
    {
      "date": "20210502",
      "tournament": "Prague Challenger Men",
      "surface": "Hard",
      "level": "C",
      "round": "SF",
      "best_of": "3",
      "result": "W",
      "opponent": "S. Baez",
      "score": "6-2 3-6 6-2"
    },
    {
      "date": "20210418",
      "tournament": "Rome Challenger Men",
      "surface": "Hard",
      "level": "C",
      "round": "SF",
      "best_of": "3",
      "result": "W",
      "opponent": "Wu Tung-Lin",
      "score": "6-2 6-1"
    },
    {
      "date": "20210401",
      "tournament": "Marbella Challenger Men",
      "surface": "Hard",
      "level": "C",
      "round": "R16",
      "best_of": "3",
      "result": "L",
      "opponent": "J. Munar",
      "score": "6-4 6-2"
    },
    {
      "date": "20210330",
      "tournament": "Marbella Challenger Men",
      "surface": "Hard",
      "level": "C",
      "round": "R32",
      "best_of": "3",
      "result": "W",
      "opponent": "L. Rosol",
      "score": "6-3 3-6 7-5"
    },
    {
      "date": "20210329",
      "tournament": "Marbella Challenger Men",
      "surface": "Hard",
      "level": "C",
      "round": "F",
      "best_of": "3",
      "result": "W",
      "opponent": "L. E. Esteve",
      "score": "7(7)-6(3) 6-4"
    },
    {
      "date": "20210328",
      "tournament": "Marbella Challenger Men",
      "surface": "Hard",
      "level": "C",
      "round": "SF",
      "best_of": "3",
      "result": "W",
      "opponent": "A. Marti Pujolras",
      "score": "7(7)-6(4) 6-2"
    },
    {
      "date": "20210326",
      "tournament": "Zadar Challenger Men",
      "surface": "Hard",
      "level": "C",
      "round": "QF",
      "best_of": "3",
      "result": "L",
      "opponent": "N. Milojevic",
      "score": "5-7 4-6"
    },
    {
      "date": "20210325",
      "tournament": "Zadar Challenger Men",
      "surface": "Hard",
      "level": "C",
      "round": "R16",
      "best_of": "3",
      "result": "W",
      "opponent": "U. Ignatik",
      "score": "2-6 6-1 6-3"
    },
    {
      "date": "20210323",
      "tournament": "Zadar Challenger Men",
      "surface": "Hard",
      "level": "C",
      "round": "R32",
      "best_of": "3",
      "result": "W",
      "opponent": "M. Bortolotti",
      "score": "1-6 3-6"
    },
    {
      "date": "20210309",
      "tournament": "St. Petersburg 2",
      "surface": "Hard",
      "level": "C",
      "round": "R32",
      "best_of": "3",
      "result": "L",
      "opponent": "E. Tiurnev",
      "score": "6-4 6-2"
    },
    {
      "date": "20210306",
      "tournament": "St. Petersburg",
      "surface": "Hard",
      "level": "C",
      "round": "SF",
      "best_of": "3",
      "result": "L",
      "opponent": "Z. Bergs",
      "score": "6(7)-7(9) 2-6"
    },
    {
      "date": "20210305",
      "tournament": "St. Petersburg",
      "surface": "Hard",
      "level": "C",
      "round": "QF",
      "best_of": "3",
      "result": "W",
      "opponent": "C. Ilkel",
      "score": "7-5 6-2"
    },
    {
      "date": "20210304",
      "tournament": "St. Petersburg",
      "surface": "Hard",
      "level": "C",
      "round": "R16",
      "best_of": "3",
      "result": "W",
      "opponent": "R. Quiroz",
      "score": "2-6 4-6"
    },
    {
      "date": "20210302",
      "tournament": "St. Petersburg",
      "surface": "Hard",
      "level": "C",
      "round": "R32",
      "best_of": "3",
      "result": "W",
      "opponent": "I. Gakhov",
      "score": "5-7 6-1 6(7)-7(9)"
    },
    {
      "date": "20210216",
      "tournament": "Potchefstroom 2",
      "surface": "Hard",
      "level": "C",
      "round": "R32",
      "best_of": "3",
      "result": "L",
      "opponent": "G. Blancaneaux",
      "score": "6-1 6-1"
    },
    {
      "date": "20210208",
      "tournament": "Potchefstroom",
      "surface": "Hard",
      "level": "C",
      "round": "F",
      "best_of": "3",
      "result": "L",
      "opponent": "M. Basic",
      "score": "6-4 6-4"
    },
    {
      "date": "20210207",
      "tournament": "Potchefstroom",
      "surface": "Hard",
      "level": "C",
      "round": "SF",
      "best_of": "3",
      "result": "W",
      "opponent": "J. Davis",
      "score": "6-1 6-1"
    },
    {
      "date": "20201127",
      "tournament": "Lima Challenger Men",
      "surface": "Hard",
      "level": "C",
      "round": "QF",
      "best_of": "3",
      "result": "L",
      "opponent": "T. Barrios",
      "score": "7(7)-6(4) 3-6 2-6"
    },
    {
      "date": "20201126",
      "tournament": "Lima Challenger Men",
      "surface": "Hard",
      "level": "C",
      "round": "R16",
      "best_of": "3",
      "result": "W",
      "opponent": "J. De Jong",
      "score": "6-0 3-6 6-1"
    },
    {
      "date": "20201123",
      "tournament": "Lima Challenger Men",
      "surface": "Hard",
      "level": "C",
      "round": "R32",
      "best_of": "3",
      "result": "W",
      "opponent": "B. Malla",
      "score": "6-2 6-3"
    },
    {
      "date": "20201116",
      "tournament": "Guayaquil Challenger Men",
      "surface": "Hard",
      "level": "C",
      "round": "R32",
      "best_of": "3",
      "result": "W",
      "opponent": "P. Krstin",
      "score": "6-1 6-4"
    },
    {
      "date": "20200921",
      "tournament": "Sibiu",
      "surface": "Hard",
      "level": "C",
      "round": "R32",
      "best_of": "3",
      "result": "L",
      "opponent": "C. Gomez-Herrera",
      "score": "6-2 6-3"
    },
    {
      "date": "20200902",
      "tournament": "Ostrava",
      "surface": "Hard",
      "level": "C",
      "round": "R32",
      "best_of": "3",
      "result": "L",
      "opponent": "I. Ivashka",
      "score": "6-4 7(7)-6(4)"
    },
    {
      "date": "20200527",
      "tournament": "O pohar prezidenta CTS",
      "surface": "Hard",
      "level": "E",
      "round": "SF",
      "best_of": "3",
      "result": "L",
      "opponent": "Z. Kolar",
      "score": "3-6 6(3)-7(7)"
    },
    {
      "date": "20200526",
      "tournament": "O pohar prezidenta CTS",
      "surface": "Hard",
      "level": "E",
      "round": "QF",
      "best_of": "3",
      "result": "W",
      "opponent": "L. Rosol",
      "score": "6(2)-7(7) 3-6"
    },
    {
      "date": "20200220",
      "tournament": "Koblenz",
      "surface": "Hard",
      "level": "C",
      "round": "R16",
      "best_of": "3",
      "result": "L",
      "opponent": "T. Machac",
      "score": "3-6 3-6"
    },
    {
      "date": "20200219",
      "tournament": "Koblenz",
      "surface": "Hard",
      "level": "C",
      "round": "R32",
      "best_of": "3",
      "result": "W",
      "opponent": "O. Otte",
      "score": "6-4 7(7)-6(4)"
    },
    {
      "date": "20200218",
      "tournament": "Koblenz",
      "surface": "Hard",
      "level": "C",
      "round": "R64",
      "best_of": "3",
      "result": "W",
      "opponent": "M. Gengel",
      "score": "4-6 3-6"
    },
    {
      "date": "20200210",
      "tournament": "Cherbourg",
      "surface": "Hard",
      "level": "C",
      "round": "R64",
      "best_of": "3",
      "result": "L",
      "opponent": "M. Zverev",
      "score": "2-6 5-7"
    },
    {
      "date": "20200128",
      "tournament": "Quimper",
      "surface": "Hard",
      "level": "C",
      "round": "R32",
      "best_of": "3",
      "result": "W",
      "opponent": "T. Lamasine",
      "score": "6-4 7(8)-6(6)"
    },
    {
      "date": "20200127",
      "tournament": "Quimper",
      "surface": "Hard",
      "level": "C",
      "round": "R64",
      "best_of": "3",
      "result": "W",
      "opponent": "P. Krstin",
      "score": "3-6 3-6"
    },
    {
      "date": "20200121",
      "tournament": "Rennes",
      "surface": "Hard",
      "level": "C",
      "round": "R32",
      "best_of": "3",
      "result": "L",
      "opponent": "T. Lamasine",
      "score": "3-6 6-3 0-6"
    },
    {
      "date": "20200120",
      "tournament": "Rennes",
      "surface": "Hard",
      "level": "C",
      "round": "R64",
      "best_of": "3",
      "result": "W",
      "opponent": "V. Durasovic",
      "score": "3-6 6-3 6-4"
    },
    {
      "date": "20191118",
      "tournament": "Maia",
      "surface": "Hard",
      "level": "C",
      "round": "R64",
      "best_of": "3",
      "result": "W",
      "opponent": "L. Faria",
      "score": "6-0 6-2"
    },
    {
      "date": "20191112",
      "tournament": "Helsinki",
      "surface": "Hard",
      "level": "C",
      "round": "R64",
      "best_of": "3",
      "result": "L",
      "opponent": "G. Blancaneaux",
      "score": "2-6 6-4 3-6"
    },
    {
      "date": "20191021",
      "tournament": "Hamburg",
      "surface": "Hard",
      "level": "C",
      "round": "R64",
      "best_of": "3",
      "result": "L",
      "opponent": "M. Moroni",
      "score": "7(7)-6(2) 3-6 6-2"
    },
    {
      "date": "20190920",
      "tournament": "Sibiu",
      "surface": "Hard",
      "level": "C",
      "round": "QF",
      "best_of": "3",
      "result": "L",
      "opponent": "C. O&apos;Connell",
      "score": "5-7 3-6"
    },
    {
      "date": "20190919",
      "tournament": "Sibiu",
      "surface": "Hard",
      "level": "C",
      "round": "R16",
      "best_of": "3",
      "result": "W",
      "opponent": "F. Coria",
      "score": "5-7 6-2 7-5"
    },
    {
      "date": "20190917",
      "tournament": "Sibiu",
      "surface": "Hard",
      "level": "C",
      "round": "R32",
      "best_of": "3",
      "result": "W",
      "opponent": "F. Arguello",
      "score": "5-7 1-6"
    },
    {
      "date": "20190916",
      "tournament": "Sibiu",
      "surface": "Hard",
      "level": "C",
      "round": "R64",
      "best_of": "3",
      "result": "W",
      "opponent": "P. Torebko",
      "score": "6-2 7(7)-6(4)"
    },
    {
      "date": "20190910",
      "tournament": "Szczecin",
      "surface": "Hard",
      "level": "C",
      "round": "R64",
      "best_of": "3",
      "result": "L",
      "opponent": "J. Jahn",
      "score": "7-5 6-4"
    },
    {
      "date": "20190729",
      "tournament": "Liberec",
      "surface": "Hard",
      "level": "C",
      "round": "R64",
      "best_of": "3",
      "result": "L",
      "opponent": "V. Safranek",
      "score": "3-6 3-6"
    },
    {
      "date": "20190723",
      "tournament": "Prague",
      "surface": "Hard",
      "level": "C",
      "round": "R64",
      "best_of": "3",
      "result": "L",
      "opponent": "P. Heller",
      "score": "2-6 3-6"
    },
    {
      "date": "20190617",
      "tournament": "Bratislava",
      "surface": "Hard",
      "level": "C",
      "round": "R64",
      "best_of": "3",
      "result": "L",
      "opponent": "L. Klein",
      "score": "7-5 6-4"
    },
    {
      "date": "20190605",
      "tournament": "Prostejov",
      "surface": "Hard",
      "level": "C",
      "round": "R16",
      "best_of": "3",
      "result": "L",
      "opponent": "P. Torebko",
      "score": "4-6 6-4 6-4"
    },
    {
      "date": "20190603",
      "tournament": "Prostejov",
      "surface": "Hard",
      "level": "C",
      "round": "R32",
      "best_of": "3",
      "result": "W",
      "opponent": "S. Darcis",
      "score": "7(7)-6(5) 3-6 4-6"
    },
    {
      "date": "20190602",
      "tournament": "Prostejov",
      "surface": "Hard",
      "level": "C",
      "round": "R64",
      "best_of": "3",
      "result": "W",
      "opponent": "J. Pospisil",
      "score": "3-6 1-6"
    },
    {
      "date": "20190506",
      "tournament": "Braga",
      "surface": "Hard",
      "level": "C",
      "round": "R64",
      "best_of": "3",
      "result": "W",
      "opponent": "J. Sels",
      "score": "6-1 2-6 0-6"
    },
    {
      "date": "20190429",
      "tournament": "Ostrava",
      "surface": "Hard",
      "level": "C",
      "round": "R64",
      "best_of": "3",
      "result": "L",
      "opponent": "J. Satral",
      "score": "3-6 6-1 6-4"
    }
  ]
}