{
  "player_id": "s0jb",
  "gs_id": "76924",
  "player_name": "Noah Schachter",
  "source": "goalserve-full",
  "updated": "2026-03-26T21:16:46.834Z",
  "matches": [
    {
      "date": "20250917",
      "tournament": "M15 Fayetteville",
      "surface": "Hard",
      "level": "I",
      "round": "R32",
      "best_of": "3",
      "rank": "",
      "opp_rank": "",
      "result": "L",
      "opponent": "S. Eriksson",
      "score": "6-4 3-6 6-4"
    },
    {
      "date": "20231104",
      "tournament": "ITF M15 Fayetteville",
      "surface": "Hard",
      "level": "I",
      "round": "SF",
      "best_of": "3",
      "rank": "",
      "opp_rank": "",
      "result": "L",
      "opponent": "D. Pham",
      "score": "3-6 1-6"
    },
    {
      "date": "20231103",
      "tournament": "ITF M15 Fayetteville",
      "surface": "Hard",
      "level": "I",
      "round": "QF",
      "best_of": "3",
      "rank": "",
      "opp_rank": "",
      "result": "W",
      "opponent": "G. Planelles Ripoll",
      "score": "7-5 4-6 4-6"
    },
    {
      "date": "20231102",
      "tournament": "ITF M15 Fayetteville",
      "surface": "Hard",
      "level": "I",
      "round": "R16",
      "best_of": "3",
      "rank": "",
      "opp_rank": "",
      "result": "W",
      "opponent": "J. Van Emburgh",
      "score": "4-6 3-6"
    },
    {
      "date": "20231101",
      "tournament": "ITF M15 Fayetteville",
      "surface": "Hard",
      "level": "I",
      "round": "R32",
      "best_of": "3",
      "rank": "",
      "opp_rank": "",
      "result": "W",
      "opponent": "J. Brumm",
      "score": "6-3 6-2"
    }
  ]
}