{
  "player_id": "s0tz",
  "gs_id": "",
  "player_name": "Rafael Segado Esteve",
  "source": "tennisabstract",
  "updated": "2026-03-29T19:44:01.702Z",
  "matches": [
    {
      "date": "2025-05-26",
      "tournament": "M15 La Nucia",
      "surface": "Clay",
      "level": "ta-import",
      "round": "R32",
      "result": "L",
      "opponent": "Diego Augusto Barreto Sanchez",
      "score": "6-2 6-2",
      "best_of": "3",
      "rank": "2077",
      "opp_rank": "607",
      "dr": "79",
      "a_pct": "0",
      "df_pct": "5",
      "first_in": "47",
      "first_pct": "27",
      "second_pct": "15",
      "bp_saved": "5",
      "match_time": "8",
      "odds": ""
    },
    {
      "date": "2024-12-09",
      "tournament": "M15 Ceuta",
      "surface": "Hard",
      "level": "ta-import",
      "round": "R16",
      "result": "L",
      "opponent": "Ivan Marrero Curbelo",
      "score": "6-2 6-3",
      "best_of": "3",
      "rank": "",
      "opp_rank": "771",
      "dr": "",
      "a_pct": "",
      "df_pct": "",
      "first_in": "",
      "first_pct": "",
      "second_pct": "",
      "bp_saved": "",
      "match_time": "",
      "odds": ""
    },
    {
      "date": "2024-12-09",
      "tournament": "M15 Ceuta",
      "surface": "Hard",
      "level": "ta-import",
      "round": "R32",
      "result": "W",
      "opponent": "Alvaro Bueno Gil",
      "score": "6-7(3) 6-4 6-2",
      "best_of": "3",
      "rank": "",
      "opp_rank": "1720",
      "dr": "",
      "a_pct": "",
      "df_pct": "",
      "first_in": "",
      "first_pct": "",
      "second_pct": "",
      "bp_saved": "",
      "match_time": "",
      "odds": ""
    },
    {
      "date": "2024-11-11",
      "tournament": "M15 Monastir",
      "surface": "Hard",
      "level": "ta-import",
      "round": "R32",
      "result": "L",
      "opponent": "Matthew William Donald",
      "score": "3-6 6-1 6-2",
      "best_of": "3",
      "rank": "",
      "opp_rank": "907",
      "dr": "",
      "a_pct": "",
      "df_pct": "",
      "first_in": "",
      "first_pct": "",
      "second_pct": "",
      "bp_saved": "",
      "match_time": "",
      "odds": ""
    },
    {
      "date": "2024-11-04",
      "tournament": "M15 Monastir",
      "surface": "Hard",
      "level": "ta-import",
      "round": "R32",
      "result": "L",
      "opponent": "Igor Kudriashov",
      "score": "6-3 3-6 6-3",
      "best_of": "3",
      "rank": "",
      "opp_rank": "1354",
      "dr": "",
      "a_pct": "",
      "df_pct": "",
      "first_in": "",
      "first_pct": "",
      "second_pct": "",
      "bp_saved": "",
      "match_time": "",
      "odds": ""
    },
    {
      "date": "2024-10-07",
      "tournament": "M15 Pontevedra",
      "surface": "Hard",
      "level": "ta-import",
      "round": "R32",
      "result": "L",
      "opponent": "Hazem Naw",
      "score": "6-3 7-6(2)",
      "best_of": "3",
      "rank": "",
      "opp_rank": "310",
      "dr": "",
      "a_pct": "",
      "df_pct": "",
      "first_in": "",
      "first_pct": "",
      "second_pct": "",
      "bp_saved": "",
      "match_time": "",
      "odds": ""
    },
    {
      "date": "2024-09-30",
      "tournament": "M25 Zaragoza",
      "surface": "Clay",
      "level": "ta-import",
      "round": "R32",
      "result": "L",
      "opponent": "Benjamin Winter Lopez",
      "score": "6-4 6-4",
      "best_of": "3",
      "rank": "",
      "opp_rank": "847",
      "dr": "",
      "a_pct": "",
      "df_pct": "",
      "first_in": "",
      "first_pct": "",
      "second_pct": "",
      "bp_saved": "",
      "match_time": "",
      "odds": ""
    },
    {
      "date": "2024-07-15",
      "tournament": "Pozoblanco CH",
      "surface": "Hard",
      "level": "ta-import",
      "round": "Q1",
      "result": "L",
      "opponent": "Albert Pedrico Kravtsov",
      "score": "6-2 6-2",
      "best_of": "3",
      "rank": "",
      "opp_rank": "884",
      "dr": "71",
      "a_pct": "0",
      "df_pct": "5",
      "first_in": "55",
      "first_pct": "23",
      "second_pct": "11",
      "bp_saved": "13",
      "match_time": "8",
      "odds": ""
    },
    {
      "date": "2024-07-08",
      "tournament": "M25 Roda de Bara",
      "surface": "Hard",
      "level": "ta-import",
      "round": "R32",
      "result": "L",
      "opponent": "Benjamin Lock",
      "score": "6-2 6-4",
      "best_of": "3",
      "rank": "",
      "opp_rank": "438",
      "dr": "",
      "a_pct": "",
      "df_pct": "",
      "first_in": "",
      "first_pct": "",
      "second_pct": "",
      "bp_saved": "",
      "match_time": "",
      "odds": ""
    },
    {
      "date": "2022-10-03",
      "tournament": "Alicante CH",
      "surface": "Hard",
      "level": "ta-import",
      "round": "Q1",
      "result": "L",
      "opponent": "Hady Habib",
      "score": "6-3 6-3",
      "best_of": "3",
      "rank": "",
      "opp_rank": "375",
      "dr": "65",
      "a_pct": "2",
      "df_pct": "4",
      "first_in": "53",
      "first_pct": "31",
      "second_pct": "20",
      "bp_saved": "10",
      "match_time": "9",
      "odds": ""
    },
    {
      "date": "2022-01-31",
      "tournament": "M15 Villena",
      "surface": "Hard",
      "level": "ta-import",
      "round": "R32",
      "result": "L",
      "opponent": "Alejandro Moro Canas",
      "score": "6-2 6-1",
      "best_of": "3",
      "rank": "",
      "opp_rank": "611",
      "dr": "",
      "a_pct": "",
      "df_pct": "",
      "first_in": "",
      "first_pct": "",
      "second_pct": "",
      "bp_saved": "",
      "match_time": "",
      "odds": ""
    }
  ]
}