{"player_id":"t0g2","sack_id":"212130","name":"Mariano Tammaro","updated":"2026-03-25","total":2,"matches":[{"id":"E1CnrRWO","date":"20260323","tournament":"CHALLENGER MEN - SINGLES: Naples (Italy) - Qualification, clay","surface":"Clay","level":"A","round":"","result":"L","opponent":"Ribecai M.","score":"0-2","best_of":"3","rank":"","opp_rank":"","src":"live"},{"id":"0Y6NkngS","date":"20260322","tournament":"CHALLENGER MEN - SINGLES: Naples (Italy) - Qualification, clay","surface":"Clay","level":"A","round":"","result":"L","opponent":"Ferrari G.","score":"2-1","best_of":"3","rank":"","opp_rank":"","src":"live"}]}